{"title":"七夕节","time_limit":1000,"memory_limit":32,"operation":{"submit":"http://acm.hdu.edu.cn/submit.php?pid=1215","submissions":"http://acm.hdu.edu.cn/status.php?first=&pid=1215&user=&lang=0&status=0","statistics":"http://acm.hdu.edu.cn/statistic.php?pid=1215","discussion":"http://acm.hdu.edu.cn/discuss/problem/list.php?problemid=1215"},"statement":[{"title":"Problem Description","content":"&#xFFFD;&#xFFFD;&#x3E6;&#xFFFD;&#xFFFD;&#xFFFD;&#xFFFD;&#xFFFD;&#xFFFD;,&#xFFFD;&#xFFFD;&#xFFFD;&#xFFFD;&#xFFFD;&#xFFFD;&#xFFFD;&#xFFFD;&#xFFFD;&#xFFFD;&#xFFFD;&#xFFFD;&#xFFFD;&#xFFFD;&#xFFFD;&#xFFFD;,&#xFFFD;&#xFFFD;&#xFFFD;&#x6B3;&#xFFFD;&#xFFFD;&#xFFFD;&#xFFFD;&#xFFFD;&#xFFFD;&#xFFFD;&#xFFFD;&#xFFFD;&#x4BB;&#xFFFD;&#x178;&#xFFFD;&#x2BE;,&#xFFFD;&#xFFFD;&#xFFFD;&#x4BA;&#xFFFD;&#xFFFD;&#xFFFD;&#xFFFD;&#xFFFD;&#xFFFD;&#xFFFD;&#xFFFD;&#xFFFD;&#xFFFD;&#xFFFD;&#xFFFD;&#xFFFD;&#xFFFD;&#xFFFD;&#x2F5;:&quot;&#xFFFD;&#xFFFD;&#xFFFD;&#xFFFD;&#xFFFD;&#xFFFD;&#x5AA;&#xFFFD;&#xFFFD;&#xFFFD;&#xFFFD;&#xFFFD;&#x1F5;&#xFFFD;&#xFFFD;&#xFFFD;&#x4BB;&#xFFFD;&#xFFFD;&#xFFFD;&#xFFFD;&#x2ED;&#xFFFD;&#xFFFD;?&#xFFFD;&#x1FE;&#x370;&#xFFFD;&#xFFFD;&#x578;&#xFFFD;&#x2BE;&#xFFFD;&#x3F5;&#x137;&#xFFFD;&#xFFFD;&#xFFFD;&#x225;&#xFFFD;&#x4B0;&#xFFFD;!&quot;<br>&#xFFFD;&#xFFFD;&#xFFFD;&#x1F7;&#x5F7;&#xFFFD;&#xFFFD;&#xFFFD;&#xFFFD;&#xFFFD;&#xFFFD;&#xFFFD;&#x2BE;&#x1F0;,&#xFFFD;&#xFFFD;&#xFFFD;&#xFFFD;&#x5AA;&#xFFFD;&#xFFFD;&#x2ED;&#xFFFD;&#xFFFD;&#xFFFD;&#xFFFD;&#xFFFD;&#x53C;&#xFFFD;&#xFFFD;&#xFFFD;&#xFFFD;&#xFFFD;&#x4BB;&#xFFFD;&#xFFFD;.&#xFFFD;&#xFFFD;&#x2BE;&#xFFFD;&#xFFFD;&#xFFFD;&#xFFFD;:<br><br><center><img style=\"max-width:100%;\" src=\"/data/images/C8-1006-1.jpg\"></center><br><br>&#xFFFD;&#xFFFD;&#xFFFD;&#xFFFD;N&#xFFFD;&#xFFFD;&#xFFFD;&#xFFFD;&#xFFFD;&#x4FE;&#xFFFD;&#xFFFD;&#xFFFD;&#xFFFD;&#xFFFD;&#xFFFD;&#x431;&#xFFFD;N&#x421;&#xFFFD;&#xFFFD;&#xFFFD;&#x731;&#xFFFD;N&#xFFFD;&#xFFFD;&#xFFFD;&#xFFFD;&#xFFFD;&#xFFFD;&#xFFFD;&#xFFFD;&#xFFFD;&#xFFFD;&#xFFFD;&#xFFFD;&#xFFFD;&#xFFFD;&#xFFFD;&#xFFFD;,&#xFFFD;&#xFFFD;12&#xFFFD;&#xFFFD;&#xFFFD;&#xFFFD;&#xFFFD;&#xFFFD;&#xFFFD;&#xFFFD;1,2,3,4,6.<br>&#xFFFD;&#xFFFD;&#xFFFD;&#xFFFD;&#x5AA;&#xFFFD;&#xFFFD;&#xFFFD;&#xFFFD;&#xFFFD;&#xFFFD;&#xFFFD;&#x4BB;&#xFFFD;&#xFFFD;&#xFFFD;&#xFFFD;?<br>","type":"description","format":"html"},{"title":"Input","content":"&#xFFFD;&#xFFFD;&#xFFFD;&#xFFFD;&#xFFFD;&#xFFFD;&#xFFFD;&#x775;&#x135;&#xFFFD;&#x4BB;&#xFFFD;&#xFFFD;&#xFFFD;&#xFFFD;&#x4BB;&#xFFFD;&#xFFFD;&#xFFFD;&#xFFFD;&#xFFFD;&#xFFFD;T(1&lt;=T&lt;=500000),&#xFFFD;&#xFFFD;&#xFFFD;&#xFFFD;&#xFFFD;&#xFFFD;&#xFFFD;&#xFFFD;&#xFFFD;&#xFFFD;&#xFFFD;&#xFFFD;&#xFFFD;&#x775;&#xFFFD;&#xFFFD;&#xFFFD;&#xFFFD;&#xFFFD;.&#x23B;&#xFFFD;&#xFFFD;&#xFFFD;&#xFFFD;T&#xFFFD;&#xFFFD;&#xFFFD;&#xFFFD;&#xFFFD;&#xFFFD;&#xFFFD;&#xFFFD;&#xFFFD;,&#xFF;&#xFFFD;&#xFFFD;&#xFFFD;&#xFFFD;&#xFFFD;&#xFFFD;&#xFFFD;&#xFFFD;&#xFFFD;&#x5BB;&#xFFFD;&#xFFFD;&#x4BB;&#xFFFD;&#xFFFD;&#xFFFD;&#xFFFD;&#xFFFD;&#xFFFD;N(1&lt;=N&lt;=500000).<br>","type":"input_format","format":"html"},{"title":"Output","content":"&#xFFFD;&#xFFFD;&#xFFFD;&#xFFFD;&#xFF;&#xFFFD;&#xFFFD;&#xFFFD;&#xFFFD;&#xFFFD;&#xFFFD;&#xFFFD;&#xFFFD;&#xFFFD;,&#xFFFD;&#xFFFD;&#xFFFD;&#xFFFD;&#xFFFD;&#x4BB;&#xFFFD;&#xFFFD;&#xFFFD;&#xFFFD;&#xFFFD;&#xFFFD;&#xFFFD;&#xFFFD;&#xFFFD;&#xFFFD;&#xFFFD;&#xFFFD;&#xFFFD;&#xFFFD;N&#xFFFD;&#xFFFD;&#xFFFD;&#xFFFD;&#x4BB;&#xFFFD;&#xFFFD;&#x131;&#xFFFD;&#xFFFD;.<br>","type":"output_format","format":"html"},{"title":"Sample Input","content":"<pre><div style=\"font-family:Courier New,Courier,monospace;\">3\n2\n10\n20</div></pre>","type":"example","format":"html"},{"title":"Sample Output","content":"<pre><div style=\"font-family:Courier New,Courier,monospace;\">1\n8\n22</div></pre>","type":"example","format":"html"},{"title":"Author","content":"Ignatius.L","type":"source","format":"html"},{"title":"Source","content":" <a href=\"/search.php?field=problem&amp;key=%BA%BC%B5%E7ACM%CA%A1%C8%FC%BC%AF%D1%B5%B6%D3%D1%A1%B0%CE%C8%FC%D6%AE%C8%C8%C9%ED%C8%FC&amp;source=1&amp;searchmode=source\"> &#xFFFD;&#xFFFD;&#xFFFD;&#xFFFD;ACM&#x2A1;&#xFFFD;&#xFFFD;&#xFFFD;&#xFFFD;&#x475;&#xFFFD;&#xFFFD;&#x461;&#xFFFD;&#xFFFD;&#xFFFD;&#xFFFD;&#x5AE;&#xFFFD;&#xFFFD;&#xFFFD;&#xFFFD;&#xFFFD;&#xFFFD; </a> ","type":"source","format":"html"}]}