{"title":"士兵队列训练问题","time_limit":1000,"memory_limit":32,"operation":{"submit":"http://acm.hdu.edu.cn/submit.php?pid=1276","submissions":"http://acm.hdu.edu.cn/status.php?first=&pid=1276&user=&lang=0&status=0","statistics":"http://acm.hdu.edu.cn/statistic.php?pid=1276","discussion":"http://acm.hdu.edu.cn/discuss/problem/list.php?problemid=1276"},"statement":[{"title":"Problem Description","content":"&#x133;&#xFFFD;&#xFFFD;&#xFFFD;&#x4FD;&#xFFFD;&#xFFFD;&#xFFFD;&#xFFFD;&#xB1;&#xFFFD;&#xFFFD;&#xFFFD;&#xFFFD;&#xFFFD;&#x475;&#xFFFD;&#xFFFD;&#xFFFD;&#xFFFD;&#xFFFD;&#xFFFD;&#xFFFD;&#xB1;&#xFFFD;&#xFFFD;&#xFFFD;&#x4BB;&#xFFFD;&#xFFFD;&#x2BC;&#xFFFD;&#xFFFD;&#x2F3;&#xFFFD;&#xFFFD;&#xFFFD;&#xFFFD;&#xFFFD;&#x3B1;&#xFFFD;&#x163;&#xFFFD;&#xFFFD;&#xFFFD;&#xFFFD;&#x173;&#xFFFD;&#x4BB;&#xFFFD;&#x43A;&#xFFFD;&#x4E3;&#xFFFD;&#x475;&#xFFFD;&#xFFFD;&#xFFFD;&#x139;&#xFFFD;&#xFFFD;&#xFFFD;&#xFFFD;&#xFFFD;&#xFFFD;&#xA3;&#xFFFD;&#xFFFD;&#xFFFD;&#x377;&#xFFFD;&#xFFFD;&#x2BC;&#x4BB;&#xFFFD;&#xFFFD;&#xFFFD;&#xFFFD;&#xFFFD;&#xFFFD;&#xFFFD;&#xFFFD;&#xFFFD;&#xFFFD;&#xFFFD;&#xFFFD;&#xFFFD;&#xFFFD;&#xFFFD;&#xFFFD;&#xFFFD;&#xFFFD;&#xFFFD;&#x133;&#xFFFD;&#xFFFD;&#x423;&#xFFFD;&#x2A3;&#xFFFD;&#xB5;&#xFFFD;&#xFFFD;&#xFFFD;&#x421;&#xFFFD;&#xFFFD;&#x177;&#xFFFD;&#xFFFD;&#xFFFD;&#xA3;&#xFFFD;&#xFFFD;&#xFFFD;&#x674;&#xFFFD;&#x377;&#xFFFD;&#xFFFD;&#x2BC;&#xFFFD;&#xFFFD;&#xFFFD;&#xFFFD;&#x4BB;&#xFFFD;&#xFFFD;&#xFFFD;&#xFFFD;&#xFFFD;&#xFFFD;&#xFFFD;&#xFFFD;&#xFFFD;&#xFFFD;&#xFFFD;&#xFFFD;&#xFFFD;&#xFFFD;&#xFFFD;&#xFFFD;&#xFFFD;&#xFFFD;&#xFFFD;&#x133;&#xFFFD;&#xFFFD;&#x423;&#xFFFD;&#x2A3;&#xFFFD;&#xB5;&#xFFFD;&#xFFFD;&#xFFFD;&#x421;&#xFFFD;&#xFFFD;&#x177;&#xFFFD;&#xFFFD;&#xFFFD;&#xA3;&#xFFFD;&#xFFFD;&#xFFFD;&#xFFFD;&#xFFFD;&#xFFFD;&#xFFFD;&#xFFFD;&#x377;&#xFFFD;&#xFFFD;&#x2BC;&#xFFFD;&#xFFFD;&#xFFFD;&#xFFFD;&#x4BB;&#xFFFD;&#xFFFD;&#xFFFD;&#xFFFD;&#xFFFD;&#xFFFD;&#xFFFD;&#xFFFD;&#xFFFD;&#xFFFD;&#xFFFD;&#xFFFD;&#xFFFD;&#xFFFD;&#xFFFD;&#xFFFD;&#xFFFD;&#x53A;&#xFFFD;&#xFFFD;&#x377;&#xFFFD;&#xFFFD;&#x2BC;&#xFFFD;&#xFFFD;&#xFFFD;&#xFFFD;&#xFFFD;&#xFFFD;&#xFFFD;&#xFFFD;&#x4BB;&#xFFFD;&#xFFFD;&#xFFFD;&#xFFFD;&#xFFFD;&#xFFFD;&#xFFFD;&#xFFFD;&#xFFFD;&#xFFFD;&#x4BB;&#xFFFD;&#xFFFD;&#xFFFD;&#xFFFD;&#xFFFD;&#xFFFD;&#xFFFD;&#xFFFD;&#x5B1;&#xFFFD;&#xFFFD;&#x2A3;&#xFFFD;&#xB5;&#xFFFD;&#xFFFD;&#xFFFD;&#xFFFD;&#xFFFD;&#xFFFD;&#xFFFD;&#xFFFD;&#xFFFD;&#xFFFD;&#xFFFD;&#xFFFD;&#xFFFD;&#xFFFD;&#xFFFD;&#x3AA;&#x5B9;&#xFFFD;&#xFFFD;<br>","type":"description","format":"html"},{"title":"Input","content":"&#xFFFD;&#xFFFD;&#xFFFD;&#xFFFD;&#xFFFD;&#x436;&#xFFFD;&#xFFFD;&#xFFFD;&#xFFFD;&#xFFFD;&#xFFFD;&#xFFFD;&#xFFFD;&#xFFFD;&#xFFFD;&#xFFFD;&#x98EC;&#xFFFD;&#xFFFD;&#x4BB;&#xFFFD;&#xFFFD;&#x3AA;&#xFFFD;&#xFFFD;&#xFFFD;&#xFFFD;N&#xFFFD;&#xFFFD;&#xFFFD;&#xFFFD;&#xFFFD;&#xFFFD;&#x3AA;N&#xFFFD;&#xFFFD;&#xFFFD;&#xB1;&#xFFFD;&#xFFFD;&#xFFFD;&#xFFFD;&#xFFFD;&#xFFFD;&#xFFFD;&#xFFFD;&#xB1;&#xFFFD;&#xFFFD;&#xFFFD;&#xFFFD;&#xFFFD;&#xFFFD;&#xFFFD;&#xFFFD;&#xFFFD;&#xFFFD;&#xFFFD;5000&#xFFFD;&#xFFFD;<br>","type":"input_format","format":"html"},{"title":"Output","content":"&#xFFFD;&#xFFFD;&#xFFFD;&#xFFFD;N&#xFFFD;&#x423;&#xFFFD;&#xFFFD;&#x5B1;&#xFFFD;&#xFFFD;&#x4E6;&#xFFFD;&#xFFFD;&#xFFFD;&#xFFFD;&#xFFFD;&#xFFFD;&#xB1;&#xFFFD;&#xFFFD;&#xFFFD;&#xFFFD;&#xFFFD;&#xFFFD;&#xFFFD;&#xFF;&#xFFFD;&#xFFFD;&#xFFFD;&#xFFFD;&#xFFFD;&#x2A3;&#xFFFD;&#xB5;&#xFFFD;&#xFFFD;&#xB1;&#xFFFD;&#xFFFD;&#xFFFD;&#xFFFD;&#xFFFD;&#x131;&#xFFFD;&#x163;&#xFFFD;&#xFFFD;&#xFFFD;&#xFFFD;&#x5AE;&#xFFFD;&#xFFFD;&#xFFFD;&#xFFFD;&#x4BB;&#xFFFD;&#xFFFD;&#xFFFD;&#x578;&#xFFFD;<br>","type":"output_format","format":"html"},{"title":"Sample Input","content":"<pre><div style=\"font-family:Courier New,Courier,monospace;\">2\n20\n40</div></pre>","type":"example","format":"html"},{"title":"Sample Output","content":"<pre><div style=\"font-family:Courier New,Courier,monospace;\">1 7 19\n1 19 37</div></pre>","type":"example","format":"html"},{"title":"Author","content":"Cai Minglun","type":"source","format":"html"},{"title":"Source","content":" <a href=\"/search.php?field=problem&amp;key=%BA%BC%B5%E7ACM%BC%AF%D1%B5%B6%D3%D1%B5%C1%B7%C8%FC%A3%A8VI%A3%A9&amp;source=1&amp;searchmode=source\"> &#xFFFD;&#xFFFD;&#xFFFD;&#xFFFD;ACM&#xFFFD;&#xFFFD;&#x475;&#xFFFD;&#xFFFD;&#x475;&#xFFFD;&#xFFFD;&#xFFFD;&#xFFFD;&#xFFFD;&#xFFFD;VI&#xFFFD;&#xFFFD; </a> ","type":"source","format":"html"}]}