{"title":"下沙小面的(1)","time_limit":1000,"memory_limit":32,"operation":{"submit":"http://acm.hdu.edu.cn/submit.php?pid=1571","submissions":"http://acm.hdu.edu.cn/status.php?first=&pid=1571&user=&lang=0&status=0","statistics":"http://acm.hdu.edu.cn/statistic.php?pid=1571","discussion":"http://acm.hdu.edu.cn/discuss/problem/list.php?problemid=1571"},"statement":[{"title":"Problem Description","content":"Lele &#xFFFD;&#xFFFD;&#xFFFD;&#xFFFD;&#x273;&#xFFFD;&#xFFFD;&#x423;&#xFFFD;&#xFFFD;&#xFFFD;&#x43A;&#x736;&#xFFFD;&#x36C;&#x467;&#xFFFD;&#xFFFD;&#xFFFD;&#xFFFD;&#xFFFD;&#xFFFD;&#xFFFD;&#xFFFD;&#xFFFD;&#xFFFD;&#x2B1;&#xFFFD;&#xFFFD;&#x4B2;&#xFFFD;&#xFFFD;&#xFFFD;&#xFFFD;&#xFFFD;&#xFFFD;&#xFFFD;&#xFFFD;&#x225;&#xFFFD;&#xFFFD;&#xFFFD;&#xFFFD;&#x36C;&#x467;&#xFFFD;&#xFFFD;&#x2F3;&#xFFFD;&#xFFFD;&#x4DF9;&#xFFFD;&#xFFFD;&#xFFFD;&#xFFFD;<br>&#xFFFD;&#xFFFD;&#xFFFD;&#xFFFD;&#x273;&#xFFFD;&#xFFFD;&#xFFFD;&#xFFFD;&#xFFFD;&#xFFFD;&#x2F7;&#xFFFD;&#xFFFD;&#xFFFD;&#x13D;&#xFFFD;&#x368;&#xFFFD;&#xFFFD;&#xFFFD;&#xFFFD;&#x12A;&#xFFFD;&#xFFFD;&#xFFFD;&#xFFFD;&#x421;&#xFFFD;&#xFFFD;&#xFFFD;&#xFFFD;&#x2E1;&#xFFFD;<br>&#xFFFD;&#xFFFD;&#xFFFD;&#xF6;&#xFFFD;&#xFFFD;&#x2E3;&#xFFFD;Lele&#xFFFD;&#xFFFD;&#x2B1;&#xFFFD;&#xFFFD;&#x4B2;&#xFFFD;&#xB8EC;&#xFFFD;&#xFFFD;&#xFFFD;&#xFFFD;&#xFFFD;&#xFFFD;&#xFFFD;&#x2A7;&#x4B5;&#xFFFD;&#x2E3;&#xFFFD;&#xFFFD;&#x739;&#xFFFD;&#xFFFD;&#xFFFD;&#xFFFD;&#xFFFD;&#x273;&#xFFFD;&#xFFFD;&#xFFFD;&#xFFFD;&#x421;&#xFFFD;&#xFFFD;&#x123;&#xFFFD;&#x4B2;&#xFFFD;&#x1F6;&#xFFFD;&#xF4;&#xFFFD;&#x4B8;&#xFFFD;&#xFFFD;&#x130;&#xFFFD;&#xFFFD;&#xFFFD;<br><br>&#xFFFD;&#xFFFD;&#xFFFD;&#xFFFD;&#xFFFD;&#xFFFD;&#x4BB;&#xFFFD;&#xC8EC;&#xFFFD;&#xFFFD;&#xFFFD;&#xFFFD;&#x538;&#xFFFD;&#xFFFD;&#xFFFD;&#xFFFD;&#xFFFD;&#xFFFD;&#x421;&#xFFFD;&#xFFFD;&#x135;&#xFFFD;&#x2FE;&#xFFFD;&#xFFFD;&#xFFFD;&#xFFFD;&#x3AA;&#xFFFD;&#x2F8;&#xFFFD;&#xFFFD;&#xF5;&#x137;&#xFFFD;&#xFFFD;&#xFFFD;&#x37B;&#xFFFD;&#xFFFD;&#xFFFD;&#xFFFD;&#xFFFD;&#xFFFD;&#xFFFD;&#xFFFD;&#xFFFD;&#xFFFD;&#xFFFD;&#x4BB;&#x429;&#xFFFD;&#xFFFD;&#xFFFD;&#xFFFD;&#xFFFD;&#x137;&#xFFFD;&#xFFFD;&#xFFFD;<br><br>1.&#xFFFD;&#xFFFD;&#xFFFD;&#xFFFD;&#xFFFD;&#xFFFD;&#x4AA;&#xFFFD;&#xFFFD;&#xFFFD;&#x3F3;&#xFFFD;&#x2B1;&#xFFFD;&#xFFFD;&#xFFFD;&#xFFFD;&#xFFFD;&#xFFFD;&#xFFFD;&#xFFFD;&#xFFFD;&#xFFFD;&#xFFFD;&#xFFFD;&#xFFFD;&#xFFFD;&#xFFFD;&#xFFFD;&#xFFFD;&#xFFFD;&#xFFFD;&#xFFFD;&#xFFFD;&#xFFFD;&#xFFFD;&#xFFFD;&#xFFFD;&#xFFFD;&#xFFFD;&#x37B;&#xFFFD;&#xFFFD;&#xFFFD;&#xFFFD;&#xFFFD;&#xFFFD;&#x3F3;&#xFFFD;&#xFFFD;&#xFFFD;<br>2.&#xFFFD;&#xFFFD;&#x429;&#xFFFD;&#x2FB;&#xFFFD;&#xFFFD;&#xFFFD;&#x3AA;&#xFFFD;&#xFFFD;&#xB7;&#xFFFD;&#xFFFD;&#xFFFD;&#xFFFD;&#xFFFD;&#xFFFD;&#xFFFD;&#xFFFD;&#x5AA;&#xFFFD;&#xFFFD;&#xFFFD;&#x53C;&#xFFFD;&#xFFFD;&#xFFFD;&#xFFFD;&#xFFFD;&#xFFFD;&#xF863;&#xFFFD;&#xFFFD;&#xFFFD;&#xFFFD;&#xFFFD;&#xFFFD;&#xFFFD;&#x6B3;&#xFFFD;&#xFFFD;&#xFFFD;1&#xFFFD;&#xFFFD;&#xFFFD;&#xFFFD;&#x4B2;&#xFFFD;&#xFFFD;&#x4AA;&#xFFFD;&#xFFFD;Lele&#xFFFD;&#xFFFD;&#xFFFD;&#xFFFD;&#xFFFD;&#x375;&#xFFFD;&#xFFFD;&#xFFFD;&#xFFFD;&#xFFFD;1&#xFFFD;&#xFFFD;&#xFFFD;&#xFFFD;&#x2B1;&#xFFFD;&#xFFFD;Lele&#xFFFD;&#xFFFD;&#x23B;&#xFFFD;&#xFFFD;&#xFFFD;&#xFFFD;&#xFFFD;&#xFFFD;&#xFFFD;&#x2F3;&#xFFFD;&#xFFFD;&#x175;&#xFFFD;&#x52D;&#xFFFD;&#xA3B38;&#xFFFD;&#xFFFD;&#xFFFD;&#xFFFD;&#xFFFD;&#xFFFD;&#xFFFD;&#xFFFD;&#xFFFD;&#xFFFD;&#xFFFD;&#xFFFD;&#xFFFD;&#xFFFD;&#xFFFD;&#xFFFD;&#x4B2;&#xFFFD;&#xFFFD;&#xFFFD;&#xFFFD;&#xFFFD;&#xFFFD;&#xFFFD;&#xFFFD;&#x3F3;&#xFFFD;&#xFFFD;&#xFFFD;<br>3.&#xFFFD;&#xFFFD;&#xFFFD;&#xFFFD;&#x421;&#xFFFD;&#xFFFD;&#x135;&#xFFFD;&#xFFFD;&#xFFFD;&#x3BB;&#x5BB;&#xFFFD;&#xFFFD;7&#xFFFD;&#xFFFD;&#xFFFD;&#xFFFD;&#xFFFD;&#xFFFD;&#xFFFD;&#xFFFD;&#xFFFD;&#xFFFD;&#x2FE;&#xFFFD;&#xFFFD;Lele&#xFFFD;&#x13C;&#xFFFD;&#x2BB;&#xFFFD;&#xFFFD;&#xFFFD;&#xFFFD;&#xFFFD;&#xFFFD;&#xFFFD;&#xFFFD;&#xFFFD;&#xFFFD;&#xFFFD;&#x2B1;&#xFFFD;&#xFFFD;&#xFFFD;&#xFFFD;&#xFFFD;&#x47E;&#xFFFD;&#xFFFD;&#xFFFD;7&#xFFFD;&#xFFFD;&#xFFFD;&#x2E3;&#xFFFD;Lele&#xFFFD;&#x372;&#xFFFD;&#xFFFD;&#xFFFD;&#xFFFD;&#xFFFD;&#xFFFD;&#xFFFD;&#xFFFD;&#xFFFD;&#xFFFD;&#x3F3;&#xFFFD;&#xFFFD;&#x2E1;&#xFFFD;<br>4.&#xFFFD;&#xFFFD;&#xFB;&#xFFFD;&#xFFFD;&#xFFFD;&#x3F3;&#xFFFD;&#x2B1;&#xFFFD;&#xFFFD;Lele&#xFFFD;&#x1FF4;&#xFFFD;&#xFFFD;&#xFFFD;&#xFFFD;&#x2ED;&#xFFFD;&#xFFFD;&#xFFFD;&#xFFFD;&#xFFFD;&#x3F3;&#xFFFD;&#xFFFD;&#xFFFD;&#x23B;&#xFFFD;&#xFFFD;&#xFFFD;&#xFFFD;&#xFFFD;&#xFFFD;&#x375;&#xFFFD;&#x13F;&#xFFFD;&#x135;&#x623;&#xFFFD;&#xFFFD;&#xFFFD;&#x23B;&#xFFFD;&#xFFFD;&#xFFFD;&#xFFFD;&#xFFFD;&#xFFFD;&#xFFFD;&#xFFFD;&#xFFFD;&#xFFFD;&#x4AA;&#x225;&#xFFFD;&#xFFFD;&#xFFFD;&#xFFFD;&#x637;&#xFFFD;&#xFFFD;&#xFFFD;&#xFFFD;&#xFFFD;&#x4B2;&#xFFFD;&#xFFFD;&#x4BB;&#xFFFD;&#xFFFD;&#xFFFD;&#xB3;&#xFFFD;&#xFFFD;&#xFFFD;&#x23B;&#xFFFD;&#xFFFD;&#x363;&#xFFFD;&#xFFFD;&#xFFFD;&#x1F8;&#xFFFD;&#x3BB;&#xFFFD;&#xFFFD;<br>5.&#xFFFD;&#xFFFD;&#xFFFD;&#xFFFD;&#xFFFD;&#xFFFD;&#xFFFD;&#xFFFD;&#x47E;&#xFFFD;&#xFB;&#xFFFD;&#x2FF;&#xFFFD;&#xFFFD;&#x2E3;&#xFFFD;Lele&#xFFFD;&#x37B;&#xFFFD;&#xFFFD;&#xFFFD;&#x52D;&#xFFFD;&#x635;&#xFFFD;&#xFFFD;&#x163;&#xFFFD;&#x5B1;&#xFFFD;&#xFFFD;&#xFFFD;&#xFFFD;&#x4BB;&#xFFFD;&#xFFFD;&#xFFFD;&#x2FF;&#xFFFD;&#xFFFD;&#xFFFD;&#xFFFD;&#x161;&#xFFFD;&#xFFFD;&#xFFFD;&#xFFFD;&#xFFFD;Lele&#xFFFD;&#xFFFD;&#xFFFD;&#x1F8;&#xFFFD;&#xFFFD;&#x637;&#xFFFD;&#xFFFD;&#x638;&#xFFFD;&#x1F0;&#xFFFD;&#xFFFD;&#x137;&#xFFFD;&#xFFFD;&#xFFFD;<br><br>&#xFFFD;&#xFFFD;&#xFFFD;&#x6A3;&#xFFFD;&#xFFFD;&#xFFFD;&#xFFFD;&#xFFFD;&#xFFFD;&#xFFFD;Lele&#x4BB;&#xFFFD;&#xFFFD;&#xFFFD;&#xFFFD;&#x535;&#xFFFD;&#xFFFD;&#xFFFD;&#xFFFD;&#xFFFD;&#xFFFD;&#xFFFD;&#xFFFD;&#xFFFD;&#xFFFD;&#xFFFD;&#xFFFD;&#xFFFD;&#xFFFD;&#xFFFD;&#xFFFD;&#xFFFD;&#x4BB;&#xFFFD;&#xA3;&#xFFFD;&#xFFFD;&#xFFFD;&#x4BB;&#xFFFD;&#xFFFD;&#x4BB;&#xFFFD;&#xFFFD;&#xFFFD;&#xFFFD;&#xFFFD;&#x2F6;&#xFFFD;&#xFFFD;&#x67E;&#xFFFD;&#xFFFD;&#xB863;","type":"description","format":"html"},{"title":"Input","content":"&#xFFFD;&#xFFFD;&#xFFFD;&#xFFFD;&#x13F;&#xFFFD;&#xFFFD;&#xFFFD;&#xFFFD;&#xFFFD;&#xFFFD;&#xFFFD;&#xFFFD;&#xFFFD;&#xFFFD;&#x521;&#xFFFD;&#xFFFD;&#xFFFD;&#xFFFD;&#x4BB;&#xFFFD;&#xFFFD;&#xFFFD;&#xFFFD;&#x53A;&#xFFFD;&#xFFFD;&#xFFFD;&#x4BB;&#xFFFD;&#xFFFD;0&#xFFFD;&#xFFFD;&#xFFFD;&#xFFFD;&#xFFFD;&#xFFFD;&#xFFFD;&#xFFFD;&#xFFFD;&#xFFFD;<br>&#xFF;&#xFFFD;&#xFFFD;&#xFFFD;&#xFFFD;&#x535;&#xFFFD;&#x4BB;&#xFFFD;&#xFFFD;&#xFFFD;&#xFFFD;&#x4BB;&#xFFFD;&#xFFFD;&#xFFFD;&#xFFFD;&#xFFFD;&#xFFFD;NCity(3&lt;=NCity&lt;=30)&#xFFFD;&#xFFFD;&#x2BE;&#xFFFD;&#xFFFD;&#x273;&#x4BB;&#xFFFD;&#xFFFD;&#xFFFD;&#x436;&#xFFFD;&#xFFFD;&#x678;&#xFFFD;&#x57E;&#xFFFD;&#xFFFD;(&#x57E;&#xFFFD;&#xFFFD;&#xFFFD;0&#xFFFD;&#xFFFD;&#x2BC;&#xFFFD;&#xFFFD;&#xFFFD;)&#xFFFD;&#xFFFD;<br>&#x23B;&#xFFFD;&#xFFFD;&#xFFFD;&#xFFFD;&#xFFFD;&#x4BB;&#xFFFD;&#xFFFD; NCity * NCity &#xFFFD;&#x13E;&#xFFFD;&#xFFFD;&#xE3B31;&#xFFFD;&#x2BE;&#x57E;&#xFFFD;&#xFFFD;&#xFFFD;&#xFFFD;&#xFFFD;&#xFFFD;&#xFFFD;&#xFFFD;&#xFFFD;&#xFFFD;&#xFFFD;&#xB863;&#xFFFD;&#xFFFD;&#xFFFD;&#xFFFD;&#xFFFD;&#xFFFD;&#xFFFD;&#xFFFD;&#xFFFD;&#xFFFD;&#x435;&#xFFFD; i &#xFFFD;&#xFFFD; &#xFFFD;&#xFFFD; j &#xFFFD;&#x435;&#xFFFD;&#x52A;&#xFFFD;&#x631;&#xFFFD;&#x2BE;&#x57E;&#xFFFD;&#xFFFD; i &#xFFFD;&#xFFFD;&#x57E;&#xFFFD;&#xFFFD; j &#xFFFD;&#x13E;&#xFFFD;&#xFFFD;&#xB863;(0&lt;=&#xFFFD;&#xFFFD;&#xFFFD;&#xFFFD;&lt;=1000)<br>&#xFFFD;&#xFFFD;&#x23B;&#xFFFD;&#xFFFD;&#xFFFD;&#xFFFD;&#x4BB;&#xFFFD;&#xFFFD;&#xFFFD;&#xFFFD;&#xFFFD;&#xFFFD;&#xFFFD;&#xFFFD; K &#xFFFD;&#xFFFD; &#xFFFD;&#xFFFD;&#x2BE;&#xFFFD;&#xFFFD;&#xFFFD;&#xFFFD;&#xFFFD;&#xFFFD;&#xFFFD;&#xFFFD;K&#xFFFD;&#xFFFD;&#x5B8;&#xFFFD;&#xE863;&#xFF;&#xFFFD;&#xFFFD;&#x5B8;&#xFFFD;&#xFFFD;&#x57C;&#x4BB;&#xFFFD;&#x421;&#xFFFD;<br>&#xFFFD;&#xFFFD;&#x5B8;&#xFFFD;&#xEFEA;&#x377;&#x3AA; UP &#xFFFD;&#xFFFD;&#x2B1;&#xFFFD;&#xA3B3D;&#xFFFD;&#xFFFD;&#xFFFD;&#xFFFD;&#xFFFD;&#xFFFD;&#xFFFD;&#x4BB;&#xFFFD;&#xFFFD;&#xFFFD;&#xFFFD;&#xFFFD;&#xFFFD; T ,&#xFFFD;&#xFFFD;&#x2BE;&#xFFFD;&#xFFFD;&#xFFFD;&#xFFFD;&#xFFFD;&#xFFFD;&#xFFFD;&#xFFFD;&#xFFFD;&#x3BB;&#xFFFD;&#xFFFD;&#xFFFD;&#xFFFD;&#x4BB;&#xFFFD;&#xFFFD;&#x4AA;&#x225;&#x57E;&#xFFFD;&#xFFFD;T(0&lt;=T&lt;NCity)&#xFFFD;&#xFFFD;&#xFFFD;&#xFFFD;&#x4AA;&#xFFFD;&#x3F3;&#xFFFD;&#xFFFD;&#xFFFD;<br>&#xFFFD;&#xFFFD;&#x5B8;&#xFFFD;&#xFFFD;&#x3AA; GO &#xFFFD;&#xFFFD;&#x2B1;&#xFFFD;&#xA3B31;&#xFFFD;&#x2BE;Lele&#x4AA;&#x5B4;&#xFFFD;&#x437;&#xFFFD;&#xFFFD;&#xFFFD;4&#xFFFD;&#xFFFD;&#xFFFD;&#xFFFD;&#x133;&#x429;&#xFFFD;&#x2FF;&#xFFFD;&#xFFFD;&#xB3;&#xFFFD;&#xFFFD;&#xFFFD;<br>&#xFFFD;&#xFFFD;&#x23B;&#xFFFD;&#xFFFD;&#xFFFD;&#xFFFD;&#xFFFD;&#xFFFD;&#xFFFD;&#xFFFD;&#x3F5;&#xFFFD;&#x2B1;&#xFB;&#xFFFD;&#x433;&#x2FF;&#x375;&#x13B;&#xFFFD;&#xFFFD;&#xFFFD;&#xFFFD;&#xFFFD;&#x37F;&#xFFFD;&#xFFFD;&#x53A;&#xFFFD;&#xFFFD;&#xFFFD;&#xFFFD;&#xFFFD;&#xFFFD;&#x5B8;&#xFFFD;&#xE863;<br><br>&#x5E2;&#xFFFD;&#x28FA;<br>&#xFFFD;&#xFFFD;&#xFF;&#xFFFD;&#xFFFD;&#xFFFD;&#xFFFD;&#x53F;&#xFFFD;&#x2BC;&#xFFFD;&#xFFFD;&#x2B1;&#xFFFD;&#xFFFD;Lele&#xFFFD;&#xFFFD;&#xFFFD;&#xFFFD;&#xFFFD;&#xFFFD;&#xFFFD;&#xFFFD;&#xFFFD;&#x363;&#xFFFD;&#xFFFD;&#x57E;&#xFFFD;&#xFFFD;0&#xFFFD;&#xFFFD;&#xFFFD;&#x4B3;&#xFFFD;&#x3AA;&#xFFFD;&#xFFFD;<br>&#xFFFD;&#xFFFD;&#xFFFD;&#xFFFD;&#xFFFD;T&#xFFFD;&#xFFFD;&#x5B8;&#xFFFD;&#xEDBC;&#xFFFD;&#xFFFD;&#xFFFD;&#xFFFD;&#x5AE;&#xFFFD;&#xE3B3B;&#xFFFD;&#xFFFD;&#xFFFD;&#xFFFD;&#xFFFD;&#xFFFD;&#xFFFD;&#xFFFD;&#xFFFD;&#xFB;&#xFFFD;&#xB3;&#xFFFD;&#xFFFD;&#xFFFD;&#xFFFD;&#xFFFD;&#xFFFD;&#xFFFD;&#xFFFD;&#xFFFD;&#x53A;&#xFFFD;&#xFFFD;&#xFFFD;&#xFFFD;&#xFFFD;&#xFFFD;&#x1E1;&#xFFFD;","type":"input_format","format":"html"},{"title":"Output","content":"&#xFFFD;&#xFFFD;&#xFFFD;&#xFFFD;&#xFFFD;&#x4BB;&#xFFFD;&#xFFFD;&#xFFFD;&#xFFFD;&#xFFFD;&#xFFFD;&#xFFFD;&#x4BB;&#xFFFD;&#xFFFD;&#xFFFD;&#xFFFD;&#xFFFD;&#xFFFD;&#xFFFD;&#xFFFD;&#xFFFD;&#xFFFD;&#x2BE;Lele&#xFFFD;&#xFFFD;&#xFFFD;&#xFFFD;&#xFFFD;&#x4BB;&#xFFFD;&#xFFFD;&#xFFFD;&#xFFFD;&#xFFFD;&#x2F6;&#xFFFD;&#xFFFD;&#x67E;&#xFFFD;&#xFFFD;&#xB863;","type":"output_format","format":"html"},{"title":"Sample Input","content":"<pre><div style=\"font-family:Courier New,Courier,monospace;\">3\n0 1 2\n1 0 3\n2 3 0\n9\nUP 1\nUP 2\nGO\nUP 2\nGO\nGO\nUP 2\nUP 1\nGO\n0</div></pre>","type":"example","format":"html"},{"title":"Sample Output","content":"<pre><div style=\"font-family:Courier New,Courier,monospace;\">7</div></pre>","type":"example","format":"html"},{"title":"Author","content":"linle","type":"source","format":"html"},{"title":"Source","content":" <a href=\"/search.php?field=problem&amp;key=HDU+2007-1+Programming+Contest&amp;source=1&amp;searchmode=source\"> HDU 2007-1 Programming Contest </a> ","type":"source","format":"html"}]}