{"title":"蜘蛛牌","time_limit":5000,"memory_limit":32,"operation":{"submit":"http://acm.hdu.edu.cn/submit.php?pid=1584","submissions":"http://acm.hdu.edu.cn/status.php?first=&pid=1584&user=&lang=0&status=0","statistics":"http://acm.hdu.edu.cn/statistic.php?pid=1584","discussion":"http://acm.hdu.edu.cn/discuss/problem/list.php?problemid=1584"},"statement":[{"title":"Problem Description","content":"&#x5A9;&#xFFFD;&#xFFFD;&#xFFFD;&#xFFFD;&#xFFFD;&#xFFFD;windows xp&#xFFFD;&#xFFFD;&#xFFFD;&#xFFFD;&#x3F5;&#x373;&#xFFFD;&#x534;&#xFFFD;&#xFFFD;&#xFFFD;&#x4BB;&#xFFFD;&#xFFFD;&#x5BD;&#xFFFD;&#xFFFD;&#xFFFD;&#xFFFD;&#x3F7;&#xFFFD;&#xFFFD;&#xFFFD;&#xFFFD;&#x3F7;&#xFFFD;&#xFFFD;&#xFFFD;&#xFFFD;&#xFFFD;&#xFFFD;&#xFFFD;&#xFFFD;&#xFFFD;&#xFFFD;&#xFFFD;&#x123;&#xFFFD;&#x5BB;&#xFFFD;&#x73D;&#xFFFD;&#xFFFD;&#xFFFD;&#xFFFD;&#x3F5;&#xFFFD;&#xFFFD;&#xFFFD;&#xFFFD;&#xFFFD;&#xFFFD;&#xFFFD;&#x4BB;&#xFFFD;&#xFFFD;&#xFFFD;&#xFFFD;&#xFFFD;&#xFFFD;&#xFFFD;&#x68E8;A&#xFFFD;&#xFFFD;&#x421;&#xFFFD;&#xFFFD;K&#xFFFD;&#xFFFD;&#xE3A63;&#xFFFD;&#xFFFD;&#xFFFD;&#xFFFD;&#xFFFD;&#x3F6;&#xFFFD;&#xFFFD;&#xFFFD;&#xFFFD;&#xFFFD;&#xFFFD;&#xFFFD;&#xFFFD;&#x430;&#xFFFD;&#x2F3;&#xFFFD;&#xFFFD;&#xFFFD;&#x17A;&#xF5;&#xFFFD;&#xFFFD;&#xFFFD;&#x2B1;&#xFFFD;&#xFFFD;&#xFFFD;&#xFFFD;&#xF4;&#xFFFD;&#xFFFD;&#x429;&#xFFFD;&#xFFFD;&#x4B2;&#xFFFD;&#xFFFD;&#xFFFD;&#xFFFD;&#x4BB;&#xFFFD;&#xFFFD;&#xFFFD;&#x1B6;&#xFFFD;&#xFFFD;&#xFFFD;&#xFFFD;&#xFFFD;&#x3F7;&#xFFFD;&#xFFFD;&#x13F;&#xFFFD;&#xFFFD;&#xFFFD;&#x1FD;&#xFFFD;&#xFFFD;&#xFFFD;&#xFFFD;&#x435;&#xFFFD;&#xFFFD;&#x1B0;&#xFFFD;&#x36C;&#x4BB;&#xFFFD;&#xFFFD;&#x26B;&#xFFFD;&#xFFFD;&#x421;&#xFFFD;&#xFFFD;&#xFFFD;&#xFFFD;&#xFFFD;&#x17A;&#xE3;&#xFFFD;&#x3AA;&#xFFFD;&#x2FC;&#xFFFD;&#xFFFD;&#xFFFD;&#xFFFD;&#xFFFD;&#xFFFD;&#xFFFD;&#xFFFD;&#xFFFD;&#x1F5;&#xFFFD;&#xFFFD;&#xFFFD;&#x3F7;&#x5BB;&#xFFFD;&#xFFFD;&#x36C;&#x4BB;&#xFFFD;&#xFFFD;&#x26B;&#xFFFD;&#xFFFD;10&#xFFFD;&#xFFFD;&#xFFFD;&#x1A3;&#xFFFD;&#xFFFD;&#xFFFD;A&#xFFFD;&#xFFFD;10&#xFFFD;&#xFFFD;&#xFFFD;&#xFFFD;&#xFFFD;&#xFFFD;&#xFFFD;&#xFFFD;&#xFFFD;&#xFFFD;&#xFFFD;&#x4BB;&#xFFFD;&#xFFFD;&#xFFFD;&#xFFFD;&#x579;&#xFFFD;&#xFFFD;&#xFFFD;&#xFFFD;&#xFFFD;&#xFFFD;&#x174;&#xFFFD;1&#xFFFD;&#xFFFD;10&#xFFFD;&#xFFFD;&#xFFFD;&#x475;&#xFFFD;i&#xFFFD;&#xFFFD;&#xFFFD;&#x3F5;&#xFFFD;&#xFFFD;&#xFFFD;&#xFFFD;&#x1B5;&#xFFFD;&#xFFFD;&#xFFFD;j&#xFFFD;&#xFFFD;&#xFFFD;&#xFFFD;&#xFFFD;&#x3E3;&#xFFFD;&#xFFFD;&#x1B6;&#xFFFD;&#xFFFD;&#xFFFD;&#xFFFD;&#xFFFD;&#x3AA;abs(i-j)&#xFFFD;&#xFFFD;&#xFFFD;&#xFFFD;&#xFFFD;&#xFFFD;&#xFFFD;&#xFFFD;&#x4AA;&#xFFFD;&#xFFFD;&#xFFFD;&#xFFFD;&#xFFFD;&#xFFFD;&#xFFFD;&#xFFFD;&#xFFFD;&#xFFFD;&#xFFFD;&#xFFFD;&#xFFFD;&#xFFFD;&#x3F7;&#xFFFD;&#xFFFD;&#xFFFD;&#xFFFD;&#x421;&#xFFFD;&#x1B6;&#xFFFD;&#xFFFD;&#xFFFD;&#xFFFD;&#xB863;<br>","type":"description","format":"html"},{"title":"Input","content":"&#xFFFD;&#xFFFD;&#x4BB;&#xFFFD;&#xFFFD;&#xFFFD;&#xFFFD;&#xFFFD;&#xFFFD;&#xFFFD;&#xFFFD;&#xFFFD;&#xFFFD;&#xFFFD;&#xFFFD;T&#xFFFD;&#xFFFD;&#xFFFD;&#xFFFD;&#x2BE;&#xFFFD;&#xFFFD;&#xFFFD;&#x775;&#xFFFD;&#xFFFD;&#xFFFD;&#xFFFD;&#xFFFD;&#xFFFD;&#xFFFD;<br>&#xFF;&#xFFFD;&#xFFFD;&#xFFFD;&#xFFFD;&#xFFFD;&#xFFFD;&#xFFFD;&#xFFFD;&#x4BB;&#xFFFD;&#x423;&#xFFFD;10&#xFFFD;&#xFFFD;&#xFFFD;&#xFFFD;&#xFFFD;&#xFFFD;&#xFFFD;&#xFFFD;&#xFFFD;&#x763;&#xFFFD;&#xFFFD;&#xFFFD;&#xFFFD;&#x775;&#x137;&#xFFFD;&#x3A7;&#xFFFD;&#xFFFD;[1,10]&#xFFFD;&#xFFFD;&#xFFFD;&#x5B1;&#xFFFD;&#xFFFD;&#x2BE;A&#xFFFD;&#xFFFD;10&#xFFFD;&#xFFFD;&#xFFFD;&#xFFFD;&#xFFFD;&#x1F1;&#xFFFD;&#x5A4;&#xFF;&#xFFFD;&#xFFFD;&#xFFFD;&#xFFFD;&#xFFFD;&#x776;&#xFFFD;&#xFFFD;&#x1FA;&#x3F7;&#xFFFD;&#xFFFD;&#x121;&#xFFFD;","type":"input_format","format":"html"},{"title":"Output","content":"&#xFFFD;&#xFFFD;&#x4E6;&#xFF;&#xFFFD;&#xFFFD;&#xFFFD;&#xFFFD;&#xFFFD;&#xFFFD;&#xFFFD;&#xFFFD;&#xFFFD;&#xFFFD;&#xFFFD;&#x421;&#xFFFD;&#x1B6;&#xFFFD;&#xFFFD;&#xFFFD;&#xFFFD;&#xB863;","type":"output_format","format":"html"},{"title":"Sample Input","content":"<pre><div style=\"font-family:Courier New,Courier,monospace;\">1\n1 2 3 4 5 6 7 8 9 10</div></pre>","type":"example","format":"html"},{"title":"Sample Output","content":"<pre><div style=\"font-family:Courier New,Courier,monospace;\">9</div></pre>","type":"example","format":"html"},{"title":"Author","content":"xhd","type":"source","format":"html"},{"title":"Source","content":" <a href=\"/search.php?field=problem&amp;key=%B6%AC%C1%B7%C8%FD%BE%C5%D6%AE%B6%FE&amp;source=1&amp;searchmode=source\"> &#xFFFD;&#xFFFD;&#xFFFD;&#xFFFD;&#xFFFD;&#xFFFD;&#xFFFD;&#xFFFD;&#x5AE;&#xFFFD;&#xFFFD; </a> ","type":"source","format":"html"}]}