{"title":"手机短号","time_limit":1000,"memory_limit":32,"operation":{"submit":"http://acm.hdu.edu.cn/submit.php?pid=2081","submissions":"http://acm.hdu.edu.cn/status.php?first=&pid=2081&user=&lang=0&status=0","statistics":"http://acm.hdu.edu.cn/statistic.php?pid=2081","discussion":"http://acm.hdu.edu.cn/discuss/problem/list.php?problemid=2081"},"statement":[{"title":"Problem Description","content":"&#x5927;&#x5BB6;&#x90FD;&#x77E5;&#x9053;&#xFF0C;&#x624B;&#x673A;&#x53F7;&#x662F;&#x4E00;&#x4E2A;11&#x4F4D;&#x957F;&#x7684;&#x6570;&#x5B57;&#x4E32;&#xFF0C;&#x540C;&#x65F6;&#xFF0C;&#x4F5C;&#x4E3A;&#x5B66;&#x751F;&#xFF0C;&#x8FD8;&#x53EF;&#x4EE5;&#x7533;&#x8BF7;&#x52A0;&#x5165;&#x6821;&#x56ED;&#x7F51;&#xFF0C;&#x5982;&#x679C;&#x52A0;&#x5165;&#x6210;&#x529F;&#xFF0C;&#x4F60;&#x5C06;&#x53E6;&#x5916;&#x62E5;&#x6709;&#x4E00;&#x4E2A;&#x77ED;&#x53F7;&#x3002;&#x5047;&#x8BBE;&#x6240;&#x6709;&#x7684;&#x77ED;&#x53F7;&#x90FD;&#x662F;&#x662F; 6+&#x624B;&#x673A;&#x53F7;&#x7684;&#x540E;5&#x4F4D;&#xFF0C;&#x6BD4;&#x5982;&#x53F7;&#x7801;&#x4E3A;13512345678&#x7684;&#x624B;&#x673A;&#xFF0C;&#x5BF9;&#x5E94;&#x7684;&#x77ED;&#x53F7;&#x5C31;&#x662F;645678&#x3002;<br>&#x73B0;&#x5728;&#xFF0C;&#x5982;&#x679C;&#x7ED9;&#x4F60;&#x4E00;&#x4E2A;11&#x4F4D;&#x957F;&#x7684;&#x624B;&#x673A;&#x53F7;&#x7801;&#xFF0C;&#x4F60;&#x80FD;&#x627E;&#x51FA;&#x5BF9;&#x5E94;&#x7684;&#x77ED;&#x53F7;&#x5417;&#xFF1F;","type":"description","format":"html","require":["katex"]},{"title":"Input","content":"&#x8F93;&#x5165;&#x6570;&#x636E;&#x7684;&#x7B2C;&#x4E00;&#x884C;&#x662F;&#x4E00;&#x4E2A;N(N &lt;= 200)&#xFF0C;&#x8868;&#x793A;&#x6709;N&#x4E2A;&#x6570;&#x636E;&#xFF0C;&#x63A5;&#x4E0B;&#x6765;&#x7684;N&#x884C;&#x6BCF;&#x4E00;&#x884C;&#x4E3A;&#x4E00;&#x4E2A;11&#x4F4D;&#x7684;&#x624B;&#x673A;&#x53F7;&#x7801;&#x3002;<br>","type":"input_format","format":"html","require":["katex"]},{"title":"Output","content":"&#x8F93;&#x51FA;&#x5E94;&#x5305;&#x62EC;N&#x884C;&#xFF0C;&#x6BCF;&#x884C;&#x5305;&#x62EC;&#x4E00;&#x4E2A;&#x5BF9;&#x5E94;&#x7684;&#x77ED;&#x53F7;&#xFF0C;&#x8F93;&#x51FA;&#x5E94;&#x4E0E;&#x8F93;&#x5165;&#x7684;&#x987A;&#x5E8F;&#x4E00;&#x81F4;&#x3002;<br>","type":"output_format","format":"html","require":["katex"]},{"title":"Sample Input","content":"<pre><div style=\"font-family:Courier New,Courier,monospace;\">2\n13512345678\n13787654321</div></pre>","type":"example","format":"html","require":["katex"]},{"title":"Sample Output","content":"<pre><div style=\"font-family:Courier New,Courier,monospace;\">645678\n654321</div></pre>","type":"example","format":"html","require":["katex"]},{"title":"Source","content":" <a href=\"/search.php?field=problem&amp;key=2006%2F1%2F15+ACM%B3%CC%D0%F2%C9%E8%BC%C6%C6%DA%C4%A9%BF%BC%CA%D4&amp;source=1&amp;searchmode=source\"> 2006/1/15 ACM&#x7A0B;&#x5E8F;&#x8BBE;&#x8BA1;&#x671F;&#x672B;&#x8003;&#x8BD5; </a> ","type":"source","format":"html","require":["katex"]}]}