{"title":"Ice_cream's world I","time_limit":1000,"memory_limit":32,"operation":{"submit":"http://acm.hdu.edu.cn/submit.php?pid=2120","submissions":"http://acm.hdu.edu.cn/status.php?first=&pid=2120&user=&lang=0&status=0","statistics":"http://acm.hdu.edu.cn/statistic.php?pid=2120","discussion":"http://acm.hdu.edu.cn/discuss/problem/list.php?problemid=2120"},"statement":[{"title":"Problem Description","content":"ice_cream&apos;s world is a rich country, it has many fertile lands. Today, the queen of ice_cream wants award land to diligent ACMers. So there are some watchtowers are set up, and wall between watchtowers be build, in order to partition the ice_cream&#x2019;s world. But how many ACMers at most can be awarded by the queen is a big problem. One wall-surrounded land must be given to only one ACMer and no walls are crossed, if you can help the queen solve this problem, you will be get a land.","type":"description","format":"html","require":["katex"]},{"title":"Input","content":"In the case, first two integers N, M (N&lt;=1000, M&lt;=10000) is represent the number of watchtower and the number of wall. The watchtower numbered from 0 to N-1. Next following M lines, every line contain two integers A, B mean between A and B has a wall(A and B are distinct). Terminate by end of file.","type":"input_format","format":"html","require":["katex"]},{"title":"Output","content":"Output the maximum number of ACMers who will be awarded.<br>One answer one line.","type":"output_format","format":"html","require":["katex"]},{"title":"Sample Input","content":"<pre><div style=\"font-family:Courier New,Courier,monospace;\">8 10\n0 1\n1 2\n1 3\n2 4\n3 4\n0 5\n5 6\n6 7\n3 6\n4 7</div></pre>","type":"example","format":"html","require":["katex"]},{"title":"Sample Output","content":"<pre><div style=\"font-family:Courier New,Courier,monospace;\">3</div></pre>","type":"example","format":"html","require":["katex"]},{"title":"Author","content":"Wiskey","type":"source","format":"html","require":["katex"]},{"title":"Source","content":" <a href=\"/search.php?field=problem&amp;key=HDU+2007-10++Programming+Contest_WarmUp&amp;source=1&amp;searchmode=source\"> HDU 2007-10  Programming Contest_WarmUp </a> ","type":"source","format":"html","require":["katex"]}]}