{"title":"熊猫阿波的故事","time_limit":1000,"memory_limit":32,"operation":{"submit":"http://acm.hdu.edu.cn/submit.php?pid=2201","submissions":"http://acm.hdu.edu.cn/status.php?first=&pid=2201&user=&lang=0&status=0","statistics":"http://acm.hdu.edu.cn/statistic.php?pid=2201","discussion":"http://acm.hdu.edu.cn/discuss/problem/list.php?problemid=2201"},"statement":[{"title":"Problem Description","content":"    &#xFFFD;&#xFFFD;&#xFFFD;&#xFFFD;&#xFFFD;&#xFFFD;&#xFFFD;&#xFFFD;&#xFFFD;&#xFFFD;&#xFFFD;&#xFFFD;&#xE8;&#xFFFD;&#x2CBF;&#xFFFD;&#xFFFD;&#x4F0;&#xFFFD;&#xFFFD;&#xFFFD;&#x2F6;&#xFFFD;&#xFFFD;&#xFFFD;&#xFFFD;&#x4F0;&#x1AC;&#xFFFD;&#xFFFD;&#xFFFD;&#xFFFD;&#x5BB;&#xFFFD;&#xFFFD;&#xFFFD;&#xFFFD;&#xFFFD;&#xFFFD;&#xFFFD;&#xFFFD;&#xE8;&#xFFFD;&#xFFFD;&#xFFFD;&#xFFFD;&#xFFFD;&#xFFFD;&#xFFFD;&#xFFFD;&#xFFFD;&#xD71;&#xFFFD;&#xFFFD;&#xFFFD;&#x4E1;&#xFFFD;&#xFFFD;&#xFFFD;&#xFFFD;&#xFFFD;&#x5B5;&#xFFFD;&#xFFFD;&#xFFFD;&#xE8;&#xFFFD;&#xFFFD;&#xFFFD;&#xFFFD;&#xFFFD;&#x534;&#x4F4;&#xFFFD;&#xFFFD;&#xFFFD;&#xFFFD;&#xFFFD;&#x5FA;&#xFFFD;&#x1FF;&#xFFFD;&#xFFFD;&#xFFFD;&#xFFFD;&#x469;&#xFFFD;&#xFFFD;&#x329;&#xFFFD;&#xFFFD;&#xFFFD;&#x53A;&#xFFFD;&#xFFFD;&#x6BA;&#xFFFD;&#x1BD;&#xFFFD;&#x235;&#x135;&#xFFFD;&#x3BB;&#xFFFD;&#xFFFD;&#x53D;&#xFFFD;&#xFFFD;&#x53D;&#xFFFD;&#x7E3;&#xFFFD;&#xFFFD;&#xFFFD;&#x3AA;&#xFFFD;&#xFFFD;&#xFFFD;&#x435;&#xFFFD;&#x4BB;&#xFFFD;&#x139;&#xFFFD;&#xFFFD;&#xFFFD;&#xFFFD;&#x2A6;&#xFFFD;&#xFFFD;&#xFFFD;&#xFFFD;&#xFFFD;&#xFFFD;&#xFFFD;&#xFFFD;&#xFFFD;&#xFFFD;&#xFFFD;&#xFFFD;&#x5FE;&#xFFFD;&#x4EA;&#xFFFD;&#xFFFD;&#xFFFD;&#xFFFD;&#x775;&#xFFFD;&#xFFFD;&#xFFFD;&#xFFFD;&#xFFFD;&#x4B2;&#x53D;&#xFFFD;&#xFFFD;&#x53D;&#xFFFD;&#xE3;&#xFFFD;&#xFFFD;&#xFFFD;&#xFFFD;&#xFFFD;&#xFF;&#xFFFD;&#xCDBC;&#xFFFD;&#xFFFD;&#xFFFD;&#xFFFD;&#xFFFD;&#xFFFD;&#xFFFD;&#xFFFD;&#x13D;&#xFFFD;&#xFFFD;&#xFFFD;&#xFFFD;&#xFFFD;&#xFFFD;&#xFFFD;&#xFFFD;&#xFFFD;&#xFFFD;&#xFFFD;&#xFFFD;&#xFFFD;&#x770;&#xFFFD;&#xFFFD;&#xFFFD;&#x3AA;&#x2A6;&#xFFFD;&#xFFFD;&#xFFFD;&#x2E1;&#xFFFD;<br>    &#x4BB;&#xFFFD;&#x563;&#xFFFD;&#xFFFD;&#xFFFD;&#xFFFD;&#xFFFD;&#xFFFD;&#x575;&#xFFFD;&#xFFFD;&#xFFFD;&#x4BB;&#xFFFD;&#xFFFD;&#xFFFD;&#xFFFD;&#xFFFD;&#xFFFD;&#xFFFD;&#xFFFD;&#xFFFD;&#xFFFD;&#xFFFD;&#xFFFD;&#x2F5;&#xFFFD;&#xFFFD;&#x4A3;&#x536;&#xFFFD;&#xFFFD;&#xFFFD;&#xFFFD;&#xFFFD;&#xFFFD;&#xFFFD;&#xFFFD;&#xFFFD;&#x67F;&#xFFFD;&#x22B;&#xFFFD;&#xFFFD;&#xFFFD;&#xFFFD;&#xFFFD;&#xFFFD;&#x18EC;&#xFFFD;&#xFFFD;&#xFFFD;&#xFFFD;&#xFFFD;&#xBC22;&#xFFFD;&#xFFFD;&#xFFFD;&#xFFFD;&#x225;&#xFFFD;&#xFFFD;&#xFFFD;&#x3B1;&#xFFFD;&#xFFFD;&#xFFFD;&#xFFFD;&#xFFFD;&#xFFFD;&#xFFFD;&#xFFFD;&#xFFFD;&#x23B;&#xFFFD;&#x738;&#xFFFD;&#xFFFD;&#x2E3;&#xFFFD;&#xFFFD;&#xFFFD;&#x3AA;&#xFFFD;&#x53C;&#xFFFD;&#xFFFD;&#xFFFD;&#xFFFD;&#xFFFD;&#xF4;&#xFFFD;&#xF6F3B;&#xFFFD;&#xFB;&#xFFFD;&#xFFFD;&#xFFFD;&#xFFFD;&#xFFFD;&#xFFFD;&#x1BD;&#xFFFD;&#x223;&#xFFFD;&#xFFFD;&#xFFFD;&#xFFFD;&#x3BF;&#xFFFD;&#xFFFD;&#x1F3;&#xFFFD;&#xFFFD;&#xFFFD;&#x225;&#xFFFD;&#xFFFD;&#x4A3;&#x536;&#xFFFD;&#xFFFD;&#xFFFD;&#xFFFD;&#xFFFD;&#xFFFD;&#xFFFD;&#xFFFD;&#xFFFD;&#xFFFD;&#xFFFD;&#xFFFD;&#xFFFD;&#xFFFD;&#xFFFD;&#xFFFD;&#xFFFD;&#xFFFD;&#xFFFD;&#xFFFD;&#xFFFD;&#x2F5;&#xFFFD;&#xFFFD;&#xFFFD;&#xFFFD;&#x13B;&#xFFFD;&#x1B1;&#xFFFD;&#xFFFD;&#xFFFD;&#xFFFD;&#xFFFD;&#xFFFD;&#xFFFD;&#xFFFD;&#xFFFD;&#xFFFD;&#xFFFD;&#xFFFD;&#xFFFD;&#xFFFD;&#xFFFD;&#xFFFD;&#xFFFD;&#xFFFD;&#xFFFD;&#xFFFD;&#xFFFD;&#xFFFD;&#xFFFD;&#x2FF;&#xFFFD;&#xFFFD;&#xFFFD;&#xFFFD;&#xFFFD;&#x5FC;&#xFFFD;&#xFFFD;&#xFFFD;&#xFFFD;&#xFFFD;&#xFFFD;&#x1B1;&#xFFFD;&#x3F5;&#x13A;&#xFFFD;&#xFFFD;&#xFFFD;(1,2,3,.....,n)&#xFFFD;&#xFFFD;&#xFFFD;&#xFFFD;&#xFFFD;&#x176;&#xFFFD;&#xFFFD;&#x3F7;&#x27B;&#xFFFD;&#xFFFD;&#xFFFD;&#xFFFD;&#xFFFD;&#xFFFD;&#x6B0;&#xFFFD;&#xFFFD;&#xFFFD;&#xFFFD;&#x1F5;&#xFFFD;&#x4BB;&#xFFFD;&#xFFFD;&#xFFFD;&#xFFFD;&#xFFFD;&#x27B;&#xFFFD;&#xFFFD;&#xFFFD;&#xFFFD;&#xFFFD;&#xFFFD;&#xFFFD;&#xFFFD;&#xFFFD;&#xFFFD;&#xFFFD;&#xFFFD;&#xFFFD;&#x4BB;&#xFFFD;&#xFFFD;&#xFFFD;&#x1FB;&#xFFFD;&#xFFFD;&#xFFFD;&#xFFFD;&#xFFFD;&#xFFFD;&#xFFFD;&#xFFFD;&#xFFFD;&#xFFFD;&#x4F5;&#xFFFD;&#x4BB;&#xFFFD;&#xFFFD;&#xFFFD;&#xFFFD;&#xFFFD;&#xFFFD;&#xFFFD;&#x2F7;&#x27B;&#xFFFD;&#xFFFD;&#xFFFD;&#xFFFD;&#xFFFD;&#xFFFD;&#xFFFD;&#xFFFD;&#xFFFD;&#x4B2;&#xFFFD;&#xFFFD;&#xFFFD;&#xFFFD;&#xFFFD;&#xFFFD;&#x1B1;&#xFFFD;&#xFFFD;&#xFFFD;&#xFFFD;&#xFFFD;&#xFFFD;&#xFFFD;&#x461;&#xFFFD;&#xFFFD;&#xFFFD;&#xFFFD;&#x4BB;&#xFFFD;&#xFFFD;&#xFFFD;&#xFFFD;&#x3BB;&#xFFFD;&#xFFFD;&#xFFFD;&#xFFFD;&#xFFFD;&#x2E1;&#xFFFD;&#xFFFD;&#x2FF;&#xFFFD;&#xFFFD;&#x1F6;&#xFFFD;&#xFFFD;&#xFFFD;&#xFFFD;&#xFFFD;&#xFFFD;&#x563;&#xFFFD;&#xFFFD;&#xFFFD;&#xFFFD;&#xFFFD;&#xFFFD;&#xB8FA;&#xFFFD;&#xFFFD;&#x23B;&#xFFFD;&#xFFFD;&#xFFFD;&#xFFFD;&#xFFFD;&#xFFFD;&#xFFFD;&#xFFFD;&#xFFFD;&#xFFFD;&#xFFFD;&#x639;&#x6DA8;&#xFFFD;&#xFFFD;&#xFFFD;&#xFFFD;&#xF4;&#xFFFD;&#xFFFD;&#x3AA;&#x2B2;&#xF4;&#x4AA;&#xFFFD;&#xFFFD;&#xFFFD;&#xFFFD;&#xFFFD;&#x623;&#xFFFD;&#xFFFD;&#xFFFD;&#x2FA;&#xFFFD;&#xFFFD;&#xFFFD;&#xFFFD;&#xFFFD;&#xFFFD;&#x435;&#xFFFD;&#xFFFD;&#xFFFD;&#x4B2;&#xFFFD;&#xFFFD;&#xFFFD;&#xFFFD;&#xFFFD;&#xFFFD;&#xFFFD;&#xFFFD;&#xFFFD;&#xFFFD;&#xFFFD;&#x3BB;&#xFFFD;&#xFFFD;&#xFFFD;&#xFFFD;&#xFFFD;&#xFFFD;&#xFFFD;&#xFFFD;&#xFFFD;&#xFFFD;&#xFFFD;&#xFFFD;&#xFFFD;&#x4BC;&#xFFFD;&#xFFFD;&#xFFFD;&#xFFFD;&#xFFFD;&#xFFFD;&#xFFFD;&#xFFFD;&#xFFFD;&#xFFFD;&#xFFFD;&#xFFFD;&#xFFFD;&#xFFFD;&#xFFFD;&#x133;&#x2FF;&#x361;&#xFFFD;<br>    &#xFFFD;&#xFFFD;&#xFFFD;&#x6B5;&#xFFFD;&#xFFFD;&#xFFFD;&#xFFFD;&#xFFFD;&#xFFFD;&#xFFFD;&#xFFFD;&#xFFFD;&#xFFFD;&#xFFFD;&#xFFFD;&#x123;&#xFFFD;&#xFFFD;&#xFFFD;&#xFFFD;&#xFFFD;&#xFFFD;&#xFFFD;&#xFFFD;&#xFFFD;&#xFFFD;&#xFFFD;&#xFFFD;&#xFFFD;&#xA3;&#xFFFD;&#xFFFD;&#xFFFD;i&#xFFFD;&#xFFFD;&#xFFFD;&#x2FF;&#xFFFD;(&#xFFFD;&#xFFFD;&#x225;&#xFFFD;&#xFFFD;&#xE8;&#xFFFD;&#xFFFD;&#xFFFD;&#xFFFD;&#xFFFD;&#xFFFD;)&#xFFFD;&#xFFFD;&#xFFFD;&#xFFFD;&#x52D;&#xFFFD;&#xFFFD;&#x1B1;&#x3BB;&#xFFFD;&#xF5;&#x138;&#xFFFD;&#xFFFD;&#xFFFD;&#xFFFD;&#x1F6;&#xFFFD;&#xFFFD;&#xFFFD;?","type":"description","format":"html"},{"title":"Input","content":"&#xFFFD;&#xFFFD;&#xFFFD;&#xFFFD;&#xFFFD;&#xFFFD;&#xFFFD;&#xFFFD;&#xFFFD;&#xFFFD;&#xFFFD;&#xFFFD;&#xFFFD;&#xFFFD;&#xFFFD;&#xFFFD;&#xFFFD;&#x763;&#xFFFD;&#xFF;&#xFFFD;&#xFFFD;&#xFFFD;&#xFFFD;&#xFFFD;&#xFFFD;&#x57C;&#x4BB;&#xFFFD;&#x423;&#xFFFD;&#xFFFD;&#xFFFD;&#xFFFD;&#xFFFD;&#xFFFD;&#xFFFD;&#xFFFD;&#xFFFD;&#xFFFD;&#xFFFD;&#xFFFD;&#xFFFD;&#xFFFD;&#xFFFD;&#xFFFD;&#x5B1;&#xFFFD;&#xFFFD;&#xFFFD;n&#xFFFD;&#xFFFD;m(n&gt;=m)&#xFFFD;&#xFFFD;n&#xFFFD;&#xFFFD;&#x2BE;&#xFFFD;&#xFFFD;&#xFFFD;&#xFFFD;n&#xFFFD;&#xFFFD;&#xFFFD;&#x2FF;&#xFFFD;(&#xFFFD;&#xFFFD;&#xFFFD;&#xFFFD;&#xFFFD;&#xFFFD;&#xFFFD;&#xFFFD;)&#xFFFD;&#xFFFD;m&#xFFFD;&#xFFFD;&#x2BE;&#xFFFD;&#xFFFD;m&#xFFFD;&#xFFFD;&#xFFFD;&#x2FF;&#x361;&#xFFFD;","type":"input_format","format":"html"},{"title":"Output","content":"&#xFFFD;&#xFFFD;&#xFFFD;&#xFFFD;&#xFF;&#xFFFD;&#xFFFD;&#xFFFD;&#xFFFD;&#xFFFD;&#x763;&#xFFFD;&#xFFFD;&#xFFFD;&#xFFFD;&#xFFFD;&#xFFFD;&#xFFFD;&#xFFFD;m&#xFFFD;&#xFFFD;&#xFFFD;&#x2FF;&#xFFFD;(&#xFFFD;&#xFFFD;&#x225;&#xFFFD;&#xFFFD;&#xE8;&#xFFFD;&#xFFFD;&#xFFFD;&#xFFFD;&#xFFFD;&#xFFFD;)&#xFFFD;&#xFFFD;&#xFFFD;&#xFFFD;&#x52D;&#xFFFD;&#xFFFD;&#x1B1;&#x3BB;&#xFFFD;&#xF5;&#x138;&#xFFFD;&#xFFFD;&#xFFFD;&#xFFFD;&#x1F6;&#xFFFD;&#xFFFD;&#xFFFD;?(&#xFFFD;&#xFFFD;&#xFFFD;&#xFFFD;&#xFFFD;&#xFFFD;&#xFFFD;2&#x3BB;&#x421;&#xFFFD;&#xFFFD;)<br>&#xFF;&#xFFFD;&#xFFFD;&#xFFFD;&#xFFFD;&#xFFFD;&#x57C;&#x4BB;&#xFFFD;&#x421;&#xFFFD;<br>","type":"output_format","format":"html"},{"title":"Sample Input","content":"<pre><div style=\"font-family:Courier New,Courier,monospace;\">2 1\n11 3</div></pre>","type":"example","format":"html"},{"title":"Sample Output","content":"<pre><div style=\"font-family:Courier New,Courier,monospace;\">0.50\n0.09</div></pre>","type":"example","format":"html"},{"title":"Author","content":"Eddy","type":"source","format":"html"}]}