{"title":"Counting Game","time_limit":1000,"memory_limit":32,"operation":{"submit":"http://acm.hdu.edu.cn/submit.php?pid=2656","submissions":"http://acm.hdu.edu.cn/status.php?first=&pid=2656&user=&lang=0&status=0","statistics":"http://acm.hdu.edu.cn/statistic.php?pid=2656","discussion":"http://acm.hdu.edu.cn/discuss/problem/list.php?problemid=2656"},"statement":[{"title":"Problem Description","content":"Let&apos;s define the number of &apos;1&apos; of X in base 2 is V(X).Now give you an X and a k, please give me the kth number Y strictly greater than X and V(X) = V(Y).","type":"description","format":"html","require":["katex"]},{"title":"Input","content":"Input includes several cases. Each case contains one line with two integers X, k. Input ends with a case X = 0 and k = 0. X is a 32-bit integer, 0 &lt; K &lt;= 50000.","type":"input_format","format":"html","require":["katex"]},{"title":"Output","content":"Every case print a integer Y in a line. Y is guaranteed to be a 32-bit integer.","type":"output_format","format":"html","require":["katex"]},{"title":"Sample Input","content":"<pre><div style=\"font-family:Courier New,Courier,monospace;\">5 1\n481 2\n0 0</div></pre>","type":"example","format":"html","require":["katex"]},{"title":"Sample Output","content":"<pre><div style=\"font-family:Courier New,Courier,monospace;\">6\n484</div></pre>","type":"example","format":"html","require":["katex"]},{"title":"Author","content":"CTW","type":"source","format":"html","require":["katex"]},{"title":"Source","content":" <a href=\"/search.php?field=problem&amp;key=%BE%F6%D5%BD%C1%FA%BB%A2%C3%C5&amp;source=1&amp;searchmode=source\"> &#x51B3;&#x6218;&#x9F99;&#x864E;&#x95E8; </a> ","type":"source","format":"html","require":["katex"]}]}