{"title":"Alexandra and Prime Numbers","time_limit":1000,"memory_limit":32,"operation":{"submit":"http://acm.hdu.edu.cn/submit.php?pid=5108","submissions":"http://acm.hdu.edu.cn/status.php?first=&pid=5108&user=&lang=0&status=0","statistics":"http://acm.hdu.edu.cn/statistic.php?pid=5108","discussion":"http://acm.hdu.edu.cn/discuss/problem/list.php?problemid=5108"},"statement":[{"title":"Problem Description","content":"Alexandra has a little brother. He is new to programming. One day he is solving the following problem: Given an positive integer N, judge whether N is prime.<br>The problem above is quite easy, so Alexandra gave him a new task: Given a positive integer N, find the minimal positive integer M, such that N/M is prime. If such M doesn&apos;t exist, output 0.<br>Help him!","type":"description","format":"html","require":["katex"]},{"title":"Input","content":"There are multiple test cases (no more than 1,000). Each case contains only one positive integer N.<br>$N \\leq 1,000,000,000$.<br>Number of cases with $N &gt; 1,000,000$ is no more than 100.","type":"input_format","format":"html","require":["katex"]},{"title":"Output","content":"For each case, output the requested M, or output 0 if no solution exists.","type":"output_format","format":"html","require":["katex"]},{"title":"Sample Input","content":"<pre><div style=\"font-family:Courier New,Courier,monospace;\">3\n4\n5\n6</div></pre>","type":"example","format":"html","require":["katex"]},{"title":"Sample Output","content":"<pre><div style=\"font-family:Courier New,Courier,monospace;\">1\n2\n1\n2</div></pre>","type":"example","format":"html","require":["katex"]},{"title":"Source","content":" <a href=\"/search.php?field=problem&amp;key=BestCoder+Round+%2319&amp;source=1&amp;searchmode=source\"> BestCoder Round #19 </a> ","type":"source","format":"html","require":["katex"]}]}