{"title":"Sitting in Line","time_limit":5000,"memory_limit":256,"operation":{"submit":"http://acm.hdu.edu.cn/submit.php?pid=5691","submissions":"http://acm.hdu.edu.cn/status.php?first=&pid=5691&user=&lang=0&status=0","statistics":"http://acm.hdu.edu.cn/statistic.php?pid=5691","discussion":"http://acm.hdu.edu.cn/discuss/problem/list.php?problemid=5691"},"statement":[{"title":"Problem Description","content":"&#x5EA6;&#x5EA6;&#x718A;&#x662F;&#x4ED6;&#x540C;&#x65F6;&#x4EE3;&#x4E2D;&#x6700;&#x4F1F;&#x5927;&#x7684;&#x6570;&#x5B66;&#x5BB6;&#xFF0C;&#x4E00;&#x5207;&#x6570;&#x5B57;&#x90FD;&#x8981;&#x542C;&#x547D;&#x4E8E;&#x4ED6;&#x3002;&#x73B0;&#x5728;&#xFF0C;&#x53C8;&#x5230;&#x4E86;&#x5EA6;&#x5EA6;&#x718A;&#x548C;&#x4ED6;&#x7684;&#x6570;&#x5B57;&#x4EC6;&#x4EBA;&#x4EEC;&#x73A9;&#x6392;&#x6392;&#x5750;&#x6E38;&#x620F;&#x7684;&#x65F6;&#x5019;&#x4E86;&#x3002;&#x6E38;&#x620F;&#x7684;&#x89C4;&#x5219;&#x5341;&#x5206;&#x7B80;&#x5355;&#xFF0C;&#x53C2;&#x4E0E;&#x6E38;&#x620F;&#x7684;N&#x4E2A;&#x6574;&#x6570;&#x5C06;&#x4F1A;&#x505A;&#x6210;&#x4E00;&#x6392;&#xFF0C;&#x4ED6;&#x4EEC;&#x5C06;&#x901A;&#x8FC7;&#x4E0D;&#x65AD;&#x4EA4;&#x6362;&#x81EA;&#x5DF1;&#x7684;&#x4F4D;&#x7F6E;&#xFF0C;&#x6700;&#x7EC8;&#x8FBE;&#x5230;&#x6240;&#x6709;&#x76F8;&#x90BB;&#x4E24;&#x6570;&#x4E58;&#x79EF;&#x7684;&#x548C;&#x6700;&#x5927;&#x7684;&#x76EE;&#x7684;&#xFF0C;&#x53C2;&#x4E0E;&#x6E38;&#x620F;&#x7684;&#x6570;&#x5B57;&#x6709;&#x6574;&#x6570;&#x4E5F;&#x6709;&#x8D1F;&#x6570;&#x3002;&#x5EA6;&#x5EA6;&#x718A;&#x4E3A;&#x4E86;&#x5728;&#x4ED6;&#x7684;&#x6570;&#x5B57;&#x4EC6;&#x4EBA;&#x9762;&#x524D;&#x5C55;&#x73B0;&#x4ED6;&#x7684;&#x6743;&#x5A01;&#xFF0C;&#x4ED6;&#x89C4;&#x5B9A;&#x67D0;&#x4E9B;&#x6570;&#x5B57;&#x53EA;&#x80FD;&#x5728;&#x5750;&#x56FA;&#x5B9A;&#x7684;&#x4F4D;&#x7F6E;&#x4E0A;&#xFF0C;&#x6CA1;&#x6709;&#x88AB;&#x5EA6;&#x5EA6;&#x718A;&#x9650;&#x5236;&#x7684;&#x6570;&#x5B57;&#x5219;&#x53EF;&#x4EE5;&#x81EA;&#x7531;&#x5730;&#x4EA4;&#x6362;&#x4F4D;&#x7F6E;&#x3002;","type":"description","format":"html","require":["katex"]},{"title":"Input","content":"&#x7B2C;&#x4E00;&#x884C;&#x4E00;&#x4E2A;&#x6574;&#x6570;$T$&#xFF0C;&#x8868;&#x793A;$T$&#x7EC4;&#x6570;&#x636E;&#x3002;<br>&#x6BCF;&#x7EC4;&#x6D4B;&#x8BD5;&#x6570;&#x636E;&#x5C06;&#x4EE5;&#x5982;&#x4E0B;&#x683C;&#x5F0F;&#x4ECE;&#x6807;&#x51C6;&#x8F93;&#x5165;&#x8BFB;&#x5165;&#xFF1A;<br><br>$N$<br><br>$a_1 p_1$<br><br>$a_2 p_2$<br><br>: <br><br>$a_N P_N$<br><br>&#x7B2C;&#x4E00;&#x884C;&#xFF0C;&#x6574;&#x6570; $N (1 \\leq N \\leq 16)$&#xFF0C;&#x4EE3;&#x8868;&#x53C2;&#x4E0E;&#x6E38;&#x620F;&#x7684;&#x6574;&#x6570;&#x7684;&#x4E2A;&#x6570;&#x3002;<br><br>&#x4ECE;&#x7B2C;&#x4E8C;&#x884C;&#x5230;&#x7B2C; $(N + 1)$ &#x884C;&#xFF0C;&#x6BCF;&#x884C;&#x4E24;&#x4E2A;&#x6574;&#x6570;&#xFF0C;$a_{i} (-10000 \\leq a_{i} \\leq 10000)$&#x3001;$p_{i} (p_{i} = -1$ &#x6216; $0 \\leq p_{i} &lt; N)$&#xFF0C;&#x4EE5;&#x7A7A;&#x683C;&#x5206;&#x5272;&#x3002;$a_{i}$&#x4EE3;&#x8868;&#x53C2;&#x4E0E;&#x6E38;&#x620F;&#x7684;&#x6570;&#x5B57;&#x7684;&#x503C;&#xFF0C;$p_{i}$&#x4EE3;&#x8868;&#x5EA6;&#x5EA6;&#x718A;&#x4E3A;&#x8BE5;&#x6570;&#x5B57;&#x6307;&#x5B9A;&#x7684;&#x4F4D;&#x7F6E;&#xFF0C;&#x5982;&#x679C;$p_{i} = -1$&#xFF0C;&#x4EE3;&#x8868;&#x8BE5;&#x6570;&#x5B57;&#x7684;&#x4F4D;&#x7F6E;&#x4E0D;&#x88AB;&#x9650;&#x5236;&#x3002;&#x5EA6;&#x5EA6;&#x718A;&#x4FDD;&#x8BC1;&#x4E0D;&#x4F1A;&#x4E3A;&#x4E24;&#x4E2A;&#x6570;&#x5B57;&#x6307;&#x5B9A;&#x76F8;&#x540C;&#x7684;&#x4F4D;&#x7F6E;&#x3002;","type":"input_format","format":"html","require":["katex"]},{"title":"Output","content":"&#x7B2C;&#x4E00;&#x884C;&#x8F93;&#x51FA;&#xFF1A;&quot;Case #i:&quot;&#x3002;$i$&#x4EE3;&#x8868;&#x7B2C;$i$&#x7EC4;&#x6D4B;&#x8BD5;&#x6570;&#x636E;&#x3002;<br><br>&#x7B2C;&#x4E8C;&#x884C;&#x8F93;&#x51FA;&#x6570;&#x5B57;&#x91CD;&#x65B0;&#x6392;&#x5217;&#x540E;&#x6700;&#x5927;&#x7684;&#x6240;&#x6709;&#x76F8;&#x90BB;&#x4E24;&#x6570;&#x4E58;&#x79EF;&#x7684;&#x548C;&#xFF0C;&#x5373;$max\\{a_1\\cdot a_2+a_2\\cdot a_3+......+a_{N-1}\\cdot a_N\\}$&#x3002;","type":"output_format","format":"html","require":["katex"]},{"title":"Sample Input","content":"<pre><div style=\"font-family:Courier New,Courier,monospace;\">2\n6\n-1 0\n2 1\n-3 2\n4 3\n-5 4\n6 5\n5\n40 -1\n50 -1\n30 -1\n20 -1\n10 -1</div></pre>","type":"example","format":"html","require":["katex"]},{"title":"Sample Output","content":"<pre><div style=\"font-family:Courier New,Courier,monospace;\">Case #1:\n-70\nCase #2:\n4600</div></pre>","type":"example","format":"html","require":["katex"]},{"title":"Source","content":" <a href=\"/search.php?field=problem&amp;key=2016%26quot%3B%B0%D9%B6%C8%D6%AE%D0%C7%26quot%3B+-+%B3%F5%C8%FC%A3%A8Astar+Round2A%A3%A9&amp;source=1&amp;searchmode=source\"> 2016&quot;&#x767E;&#x5EA6;&#x4E4B;&#x661F;&quot; - &#x521D;&#x8D5B;&#xFF08;Astar Round2A&#xFF09; </a> ","type":"source","format":"html","require":["katex"]}]}