{"title":"Game","time_limit":1000,"memory_limit":32,"operation":{"submit":"http://acm.hdu.edu.cn/submit.php?pid=6312","submissions":"http://acm.hdu.edu.cn/status.php?first=&pid=6312&user=&lang=0&status=0","statistics":"http://acm.hdu.edu.cn/statistic.php?pid=6312","discussion":"http://acm.hdu.edu.cn/discuss/problem/list.php?problemid=6312"},"statement":[{"title":"Problem Description","content":"Alice and Bob are playing a game.<br>The game is played on a set of positive integers from 1 to n.<br>In one step, the player can choose a positive integer from the set, and erase all of its divisors from the set. If a divisor doesn&apos;t exist it will be ignored.<br>Alice and Bob choose in turn, the one who cannot choose (current set is empty) loses.<br>Alice goes first, she wanna know whether she can win. Please judge by outputing &apos;Yes&apos; or &apos;No&apos;.","type":"description","format":"html","require":["katex"]},{"title":"Input","content":"There might be multiple test cases, no more than 10. You need to read till the end of input.<br>For each test case, a line containing an integer n. ($1 \\leq n \\leq 500$)<br>","type":"input_format","format":"html","require":["katex"]},{"title":"Output","content":"A line for each test case, &apos;Yes&apos; or &apos;No&apos;.<br>","type":"output_format","format":"html","require":["katex"]},{"title":"Sample Input","content":"<pre><div style=\"font-family:Courier New,Courier,monospace;\">1</div></pre>","type":"example","format":"html","require":["katex"]},{"title":"Sample Output","content":"<pre><div style=\"font-family:Courier New,Courier,monospace;\">Yes</div></pre>","type":"example","format":"html","require":["katex"]},{"title":"Source","content":" <a href=\"/search.php?field=problem&amp;key=2018+Multi-University+Training+Contest+2&amp;source=1&amp;searchmode=source\"> 2018 Multi-University Training Contest 2 </a> ","type":"source","format":"html","require":["katex"]}]}