{"title":"Rikka with Badminton","time_limit":1000,"memory_limit":512,"operation":{"submit":"http://acm.hdu.edu.cn/submit.php?pid=6425","submissions":"http://acm.hdu.edu.cn/status.php?first=&pid=6425&user=&lang=0&status=0","statistics":"http://acm.hdu.edu.cn/statistic.php?pid=6425","discussion":"http://acm.hdu.edu.cn/discuss/problem/list.php?problemid=6425"},"statement":[{"title":"Problem Description","content":"In the last semester, Rikka joined the badminton club.<br><br>There are $n$ students in the badminton club, some of them have rackets, and some of them have balls. Formally, there are $a$ students have neither rackets nor balls, $b$ students have only rackets, $c$ students have only balls, and $d$ students have both rackets and balls. $(a+b+c+d=n)$<br><br>This week, the club is going to organize students to play badminton. Each student can choose to take part in or not freely. So there are $2^n$ possible registration status. <br><br>To play badminton, there must be at least two students who have rackets and at least one students who have balls. So if there aren&apos;t enough balls or rackets, the activity will fail. <br><br>Now, Rikka wants to calculate the number of the status among all $2^n$ possible registration status which will make the activity fail.","type":"description","format":"html"},{"title":"Input","content":"The first line contains a single number $t(1 \\leq t \\leq 10^3)$, the number of testcases.<br><br>For each testcase, the first line contains four integers $a,b,c,d(0 \\leq a,b,c,d \\leq 10^7,a+b+c+d \\geq 1)$.","type":"input_format","format":"html"},{"title":"Output","content":"For each testcase, output a single line with a single integer, the answer modulo $998244353$.","type":"output_format","format":"html"},{"title":"Sample Input","content":"<pre><div style=\"font-family:Courier New,Courier,monospace;\">3\n1 1 1 1\n2 2 2 2\n3 4 5 6</div></pre>","type":"example","format":"html"},{"title":"Sample Output","content":"<pre><div style=\"font-family:Courier New,Courier,monospace;\">12\n84\n2904</div></pre>","type":"example","format":"html"},{"title":"Source","content":" <a href=\"/search.php?field=problem&amp;key=2018+Multi-University+Training+Contest+9&amp;source=1&amp;searchmode=source\"> 2018 Multi-University Training Contest 9 </a> ","type":"source","format":"html"}]}