{"title":"商业竞争","time_limit":1000,"memory_limit":100,"operation":{"submit":"http://acm.hdu.edu.cn/submit.php?pid=6475","submissions":"http://acm.hdu.edu.cn/status.php?first=&pid=6475&user=&lang=0&status=0","statistics":"http://acm.hdu.edu.cn/statistic.php?pid=6475","discussion":"http://acm.hdu.edu.cn/discuss/problem/list.php?problemid=6475"},"statement":[{"title":"Problem Description","content":"&#xFFFD;&#xFFFD;&#xFFFD;&#xFFFD;&#xFFFD;&#xFFFD;&#xFFFD;&#xFFFD;&#xFFFD;&#xFFFD;&#x4AA;&#xFFFD;&#xFFFD;&#xFFFD;&#x4BB;&#xFFFD;&#xFFFD;&#x22B;&#xFFFD;&#xFFFD;&#xFFFD;&#xFFFD;&#xFFFD;&#xFFFD;&#xFFFD;&#xFFFD;&#x4F5;&#xFFFD;&#xFFFD;&#xFFFD;&#xFFFD;&#xFFFD;&#xFFFD;&#xFFFD;&#xFFFD;&#xFFFD;&#x675;&#xFFFD;&#xFFFD;&#xFFFD;&#xFFFD;&#xFFFD;&#xFFFD;&#xFFFD;&#xFFFD;&#x286A;&#xFFFD;&#xFFFD;&#xFFFD;&#xFFFD;&#x3B7;&#xFFFD;&#xFFFD;&#xFFFD;&#x1A1;&#xFFFD;<br><br>&#xFFFD;&#xFFFD;&#xFFFD;&#xFFFD;&#x4BB;&#xFFFD;&#xFFFD;&#xFFFD;&#xFFFD;&#xFFFD;&#x4F9;&#xFFFD;&#xFFFD;&#xFFFD;&#x433;&#xFFFD;&#xFFFD;&#xFFFD;&#xFFFD;&#x43D;&#x9863;&#xFFFD;&#xFFFD;&#x139;&#xFFFD;&#xFFFD;&#xFFFD;&#xFFFD;&#x1F8;&#xFFFD;&#x4AA;&#xFFFD;&#xFFFD;&#xFFFD;&#xFFFD;&#x139;&#xFFFD;&#x2FE;&#xFFFD;&#xFFFD;&#xFFFD;&#xFFFD;&#x4BB;&#xFFFD;&#xFFFD;&#xFFFD;&#x2B1;&#xFFFD;&#xFFFD;&#x225;&#xFFFD;&#xFFFD;&#xFFFD;&#xFFFD;&#xFFFD;&#xFFFD;&#xFFFD;&#x1F5;&#x139;&#xFFFD;&#x6863;&#xFFFD;&#xFFFD;&#x4B9;&#xFFFD;&#x2FE;&#x4BB;&#xFFFD;&#xFFFD;&#xFFFD;&#xFFFD;&#xFFFD;&#xFFFD;&#xFFFD;&#xFFFD;$n$&#xFFFD;&#xFFFD;&#xFFFD;&#xFFFD;&#xFFFD;&#x1AC;&#xFFFD;&#x3A3;&#xFFFD;&#xFF;&#xFFFD;&#xFFFD;&#x1AC;&#xFFFD;&#xFFFD;&#xFFFD;&#xFFFD;&#xFFFD;&#x5BB;&#xFFFD;&#x732;&#xFFFD;&#xFFFD;&#xFFFD;&#x4BB;&#xFFFD;&#x3A3;&#xFFFD;&#xFFFD;&#xFFFD;$i$&#xFFFD;&#xFFFD;&#x1AC;&#xFFFD;&#xFFFD;&#xFFFD;&#xFFFD;&#x4AA;&#x57C;&#xFFFD;&#xFFFD;$w_i$&#xFFFD;&#xFFFD;&#x135;&#xFFFD;&#xFFFD;&#x6A3;&#xFFFD;&#xFFFD;&#x6B5;&#xFFFD;$k$&#xFFFD;&#xFFFD;&#xFFFD;&#xFFFD;&#xFFFD;&#x1AC;&#xFFFD;&#x3B8;&#xFFFD;&#xFFFD;&#xFFFD;&#x4B9;&#xFFFD;&#x2FE;&#xFFFD;&#xFFFD;&#xFFFD;&#xFFFD;&#xFFFD;&#x13E;&#xFFFD;&#xFFFD;&#xFFFD;&#xFFFD;&#xFFFD;&#x3AA;$k\\times a_i+b_i$&#xFFFD;&#xFFFD;&#x4BB;&#xFFFD;&#xFFFD;&#x1AC;&#xFFFD;&#xFFFD;&#x4BB;&#xFFFD;&#xFFFD;&#xFFFD;&#xFFFD;&#x2BC;&#xFFFD;&#xFFFD;&#xFFFD;&#x17E;&#x372;&#xFFFD;&#xFFFD;&#xFFFD;&#xFFFD;&#xFFFD;&#xFFFD;&#x3E1;&#xFFFD;<br><br>&#xFFFD;&#xFFFD;&#xFFFD;&#xFFFD;&#x4AA;&#xFFFD;&#xFFFD;$[l,r]$&#x5AE;&#xFFFD;&#xFFFD;&#x461;&#xFFFD;&#xFFFD;&#x4BB;&#xFFFD;&#xFFFD;&#xFFFD;&#xFFFD;&#xFFFD;&#xFFFD;&#xFFFD;&#xFFFD;$k$&#xFFFD;&#xFFFD;&#xFFFD;&#x6B5;&#xFFFD;$k$&#xFFFD;&#xCCA5;&#xFFFD;&#xFFFD;&#xFFFD;&#xFFFD;&#x4B9;&#xFFFD;&#x2FE;&#xFFFD;&#x139;&#xFFFD;&#x6863;&#xFFFD;&#xFFFD;&#x4B9;&#xFFFD;&#x2FE;&#xFFFD;&#xFFFD;&#xFFFD;&#xFFFD;&#xFFFD;&#x5AA;$k$&#xFFFD;&#xE3B3B;&#xFFFD;&#xFFFD;&#xFFFD;&#xFFFD;&#xFFFD;&#xFFFD;&#xFFFD;&#x461;&#xFFFD;&#xFFFD;&#x4BB;&#x429;&#xFFFD;&#xFFFD;&#xFFFD;&#xFFFD;&#xFFFD;&#x432;&#xFFFD;&#xFFFD;&#x163;&#xFFFD;&#x2B9;&#xFFFD;&#xFFFD;&#xFFFD;&#xFFFD;&#xFFFD;&#x1F5;&#xFFFD;&#xFFFD;&#xFFFD;&#xFFFD;&#xFFFD;&#xFFFD;&#xFFFD;&#xFFFD;&#xFFFD;&#xFFFD;(&#x4B2;&#xFFFD;&#xFFFD;&#xFFFD;&#xFFFD;&#x4BB;&#xFFFD;&#xFFFD;&#xFFFD;&#xFFFD;&#x6DBC;&#xFFFD;&#xFFFD;&#xFFFD;&#xFFFD;&#xFFFD;&#x163;&#xFFFD;&#xFFFD;&#xFFFD;&#xFFFD;&#xFFFD;&#xFFFD;&#xFFFD;&#x1F8;&#xFFFD;&#xFFFD;&#xFFFD;&#xFFFD;&#xFFFD;&#x13B;&#xFFFD;)&#xFFFD;&#xFFFD;&#xFFFD;&#xFFFD;&#xFFFD;&#xFFFD;&#xFF;&#xFFFD;&#xFFFD;&#xFFFD;&#xFFFD;&#xFFFD;&#x5BB;&#xFFFD;&#x732;&#xFFFD;&#xFFFD;&#xFFFD;&#xFFFD;&#x733;&#xFFFD;&#xFFFD;&#x232;&#xFFFD;&#xFFFD;&#xFFFD;&#xFFFD;&#xFFFD;$m$&#xFFFD;&#xFFFD;&#x139;&#xFFFD;&#x68EC;&#xFFFD;&#xFFFD;&#xFFFD;&#x535;&#xFFFD;&#xFFFD;&#xFFFD;&#xFFFD;&#x6B2;&#xFFFD;&#xFFFD;&#xFFFD;&#x2B1;&#xFFFD;&#xFFFD;&#xFFFD;&#xFFFD;&#xFFFD;&#xFFFD;&#x4B2;&#xFFFD;&#xFFFD;&#xFFFD;&#xFFFD;&#xFFFD;&#xFFFD;&#xFFFD;&#xFFFD;&#xFFFD;&#xFFFD;&#x4BB;&#x429;&#xFFFD;&#xFFFD;&#x6863;<br><br>&#xFFFD;&#xFFFD;&#x4B5;&#xFFFD;&#xFFFD;&#xFFFD;&#xFFFD;&#xFFFD;&#x1F2;&#x43F;&#xFFFD;&#x123;&#xFFFD;&#xFFFD;&#x537;&#xFFFD;&#x5EC;&#xFFFD;&#xFFFD;&#x53D;&#xFFFD;&#x8EC;&#xFFFD;&#xFFFD;&#x5EC;&#xFFFD;&#x13E;&#xFFFD;&#x53D;&#xFFFD;&#x661;&#xFFFD;&#xFFFD;&#xFFFD;&#x461;&#xFFFD;&#xFFFD;&#x4BB;&#xFFFD;&#xFFFD;&#xFFFD;&#xFFFD;&#xFFFD;&#xFFFD;&#x2B5;&#xFFFD;$k$&#xFFFD;&#xFFFD;&#x2B9;&#xFFFD;&#xF8;&#xF9;&#xFFFD;&#x2FE;&#xFFFD;&#xFFFD;&#xFFFD;&#xFFFD;&#xFFFD;&#xFFFD;&#xFFFD;&#x172;&#xFFFD;&#xFFFD;&#xFFFD;&#x376;&#xFFFD;&#x179;&#xFFFD;&#xFFFD;&#xFFFD;&#xFFFD;&#xFFFD;&#xFFFD;&#xFFFD;&#xFFFD;&#xFFFD;&#xFFFD;&#xFFFD;&#x421;&#xFFFD;&#xFFFD;","type":"description","format":"html"},{"title":"Input","content":"&#xFFFD;&#xFFFD;&#x4BB;&#xFFFD;&#x430;&#xFFFD;&#xFFFD;&#xFFFD;&#x4BB;&#xFFFD;&#xFFFD;&#xFFFD;&#xFFFD;&#xFFFD;&#xFFFD;&#xFFFD;&#xFFFD;$T(1\\leq T\\leq 10)$&#xFFFD;&#xFFFD;&#xFFFD;&#xFFFD;&#x2BE;&#xFFFD;&#xFFFD;&#xFFFD;&#xFFFD;&#xFFFD;&#xFFFD;&#xFFFD;&#x775;&#xFFFD;&#xFFFD;&#xFFFD;&#xFFFD;&#xFFFD;&#xFFFD;&#xFFFD;<br><br>&#xFF;&#xFFFD;&#xFFFD;&#xFFFD;&#xFFFD;&#xFFFD;&#x775;&#xFFFD;&#x4BB;&#xFFFD;&#x430;&#xFFFD;&#xFFFD;&#xFFFD;&#xFFFD;&#x138;&#xFFFD;&#xFFFD;&#xFFFD;&#xFFFD;&#xFFFD;&#xFFFD;&#xFFFD;$n,m,l,r(1\\leq n,m\\leq 500,1\\leq l\\leq r\\leq 10^6)$&#xFFFD;&#xFFFD;&#xFFFD;&#x5B1;&#xFFFD;&#xFFFD;&#x2BE;&#xFFFD;&#xFFFD;&#xFFFD;&#x1AC;&#xFFFD;&#x3B5;&#xFFFD;&#xFFFD;&#xFFFD;&#xFFFD;&#xFFFD;&#xFFFD;&#xFFFD;&#xFFFD;&#xFFFD;&#xFFFD;&#x6B5;&#xFFFD;&#xFFFD;&#xFFFD;&#xFFFD;&#xFFFD;&#xFFFD;&#x53C;&#xFFFD;&#x461;&#xFFFD;&#xFFFD;&#x137;&#xFFFD;&#x3A7;&#xFFFD;&#xFFFD;<br><br>&#xFFFD;&#xFFFD;&#xFFFD;&#xFFFD;&#xFFFD;&#xFFFD;$n$&#xFFFD;&#x423;&#xFFFD;&#xFF;&#xFFFD;&#xFFFD;&#xFFFD;&#xFFFD;&#xFFFD;&#xFFFD;&#xFFFD;&#xFFFD;&#xFFFD;&#xFFFD;$a_i,b_i,w_i(-10^6\\leq a_i\\leq 10^6,-10^{12}\\leq b_i\\leq 10^{12},1\\leq w_i\\leq m)$&#xFFFD;&#xFFFD;&#xFFFD;&#xFFFD;&#xFFFD;&#xFFFD;&#xFFFD;&#xFFFD;&#xFFFD;&#xFFFD;&#xFF;&#xFFFD;&#xFFFD;&#xFFFD;&#xFFFD;&#xFFFD;&#x1AC;&#xFFFD;&#x3A1;&#xFFFD;","type":"input_format","format":"html"},{"title":"Output","content":"&#xFFFD;&#xFFFD;&#xFFFD;&#xFFFD;&#xFF;&#xFFFD;&#xFFFD;&#xFFFD;&#xFFFD;&#xFFFD;&#xFFFD;&#xFFFD;&#xFFFD;&#xFFFD;&#x4BB;&#xFFFD;&#xFFFD;&#x4BB;&#xFFFD;&#xFFFD;&#xFFFD;&#xFFFD;&#xFFFD;&#xFFFD;&#xFFFD;&#xFFFD;&#xFFFD;&#xFFFD;&#xFFFD;&#xF9;&#xFFFD;&#x2FE;&#xFFFD;&#xFFFD;&#xFFFD;&#xFFFD;&#xFFFD;&#xFFFD;&#xFFFD;&#x172;&#xFFFD;&#xFFFD;&#xFFFD;&#x376;&#xFFFD;&#x179;&#xFFFD;&#xFFFD;&#xFFFD;&#xFFFD;&#xFFFD;&#xFFFD;&#xFFFD;&#xFFFD;&#xFFFD;&#xFFFD;&#xFFFD;&#xFFFD;&#x421;&#xFFFD;&#xFFFD;&#xFFFD;&#xFFFD;&#x5B5;&#xFFFD;&#xFFFD;","type":"output_format","format":"html"},{"title":"Sample Input","content":"<pre><div style=\"font-family:Courier New,Courier,monospace;\">1\n3 5 1 5\n-3 5 2\n-2 2 3\n2 5 3</div></pre>","type":"example","format":"html"},{"title":"Sample Output","content":"<pre><div style=\"font-family:Courier New,Courier,monospace;\">9</div></pre>","type":"example","format":"html"},{"title":"Author","content":"Claris","type":"source","format":"html"},{"title":"Source","content":" <a href=\"/search.php?field=problem&amp;key=Championship&amp;source=1&amp;searchmode=source\"> Championship </a> ","type":"source","format":"html"}]}