{"title":"A Very Easy Graph Problem","time_limit":2500,"memory_limit":64,"operation":{"submit":"http://acm.hdu.edu.cn/submit.php?pid=6832","submissions":"http://acm.hdu.edu.cn/status.php?first=&pid=6832&user=&lang=0&status=0","statistics":"http://acm.hdu.edu.cn/statistic.php?pid=6832","discussion":"http://acm.hdu.edu.cn/discuss/problem/list.php?problemid=6832"},"statement":[{"title":"Problem Description","content":"An undirected connected graph has $n$ nodes and $m$ edges, The $i$-th edge&#x2019;s length is $2^i$.  Each node $i$ has a value $a_i$,  which is either $0$ or $1$.  You need to calculate:<br><br>$$<br>\\sum_{i=1}^{n}\\sum_{j=1}^{n}d(i,j)\\times [a_i=1\\wedge a_j=0]<br>$$<br><br>$d(i,j)$ indicates the shortest distance between $i$ and $j$. $[\\ ]$ is the Iverson bracket. $\\wedge$ indicates $\\texttt{AND}$.<br> <br>Because the answer may be too large,  please output the answer modulo $10^9 + 7$.","type":"description","format":"html"},{"title":"Input","content":"The first line contains one integer $T$($1\\le T \\le 8$)&#xFF0C;indicating the number of test cases.<br><br>The second line contains two ingeters $n,m$($1\\le n\\le 10^5,1\\le m\\le 2\\times 10^5$).<br><br>The third line contains $n$ positive integers $a_1,a_2,...,a_n(a_i = 0$ or $1$) &#x2014;&#x2014; the value of the nodes.<br><br>The following $m$ lines contain two ingeters $u,v(1<br>\\le u,v \\le n)$, and the $i$-th line represents the i-th undirected edge&#x2019;s length is $2^i$, between node $u$ and $v$.<br><br>The sum of $n,m$ is no more than $2\\times 10^5$.","type":"input_format","format":"html"},{"title":"Output","content":"Print a single integer&#x2014;&#x2014; the value of the answer modulo $10^9+7$.","type":"output_format","format":"html"},{"title":"Sample Input","content":"<pre><div style=\"font-family:Courier New,Courier,monospace;\">1\n3 2\n0 1 0 \n3 1\n3 2</div></pre>","type":"example","format":"html"},{"title":"Sample Output","content":"<pre><div style=\"font-family:Courier New,Courier,monospace;\">10</div></pre>","type":"example","format":"html"},{"title":"Source","content":" <a href=\"/search.php?field=problem&amp;key=2020+Multi-University+Training+Contest+6&amp;source=1&amp;searchmode=source\"> 2020 Multi-University Training Contest 6 </a> ","type":"source","format":"html"}]}